{
  "meta": {
    "schema_version": "1.0",
    "last_updated_by": "hardware",
    "last_updated_at": "2026-03-31T14:28:46.244264",
    "build_sequence": [
      "requirements",
      "hardware"
    ],
    "corrections_log": []
  },
  "requirements": {
    "generation_mode": "MIGRATION",
    "migration_info": {
      "has_reference": true,
      "reference_family": "TC3xx",
      "target_family": "TC3xx",
      "migration_required": false,
      "driver_mappings": {
        "IfxGtm_Tom_PwmHl": "IfxGtm_Tom_Pwm"
      },
      "header_mappings": {
        "IfxGtm_Tom_PwmHl.h": "IfxGtm_Tom_Pwm.h"
      },
      "api_changes": [
        {
          "from": "IfxGtm_Tom_PwmHl_*",
          "to": "IfxGtm_Tom_Pwm_*",
          "reason": "User-requested replacement of PwmHl with Pwm on TOM"
        },
        {
          "from": "IfxGtm_Tom_PwmHl_initConfig",
          "to": "IfxGtm_Tom_Pwm_initConfig",
          "reason": "Driver API alignment (mid-level TOM PWM config)"
        },
        {
          "from": "IfxGtm_Tom_PwmHl_init",
          "to": "IfxGtm_Tom_Pwm_init",
          "reason": "Driver API alignment (mid-level TOM PWM init)"
        }
      ],
      "function_names_to_preserve": [
        "initGtmTom3phInv",
        "updateGtmTom3phInvDuty"
      ],
      "explicit_driver_upgrade": true,
      "target_driver": "IfxGtm_Tom_Pwm"
    },
    "peripheral_requirement": {
      "type": "GTM_TOM",
      "driver_available": true,
      "driver_name": "IfxGtm_Tom_Pwm",
      "purpose": "3-phase center-aligned PWM on TOM1 at 20 kHz with synchronous multi-channel update; replace PwmHl with Pwm while preserving pins and module API names.",
      "driver_locked": true,
      "driver_selection_source": "user_explicit"
    },
    "signal_requirements": {
      "preserve_pins": true,
      "tom_module": "TOM1",
      "channel_assignments": {
        "U": {
          "high_side_pin": "P00.3 (TOM1 CH2)",
          "low_side_pin": "P00.2 (TOM1 CH1)"
        },
        "V": {
          "high_side_pin": "P00.5 (TOM1 CH4)",
          "low_side_pin": "P00.4 (TOM1 CH3)"
        },
        "W": {
          "high_side_pin": "P00.7 (TOM1 CH6)",
          "low_side_pin": "P00.6 (TOM1 CH5)"
        }
      },
      "pinmap_headers": [
        "IfxGtm_PinMap.h"
      ],
      "synchronous_update": {
        "enabled": true,
        "method": "TOM1 TGC shadow transfer for all used channels (CH1..CH6)",
        "update_trigger": "software trigger after all new duties are staged"
      },
      "complementary_mode": {
        "enabled": false,
        "note": "Default to single-ended using HS pins P00.3/5/7 only. If complementary is later required, Pwm driver does not provide hardware dead-time; consider switching to IfxGtm_Tom_Dtm_PwmHl or retain PwmHl for dead-time management."
      },
      "single_ended_pins_active": [
        "P00.3 (CH2)",
        "P00.5 (CH4)",
        "P00.7 (CH6)"
      ]
    },
    "timing_requirements": {
      "pwm_frequency_hz": 20000,
      "alignment": "center",
      "clock_source": "GTM CMU_CLK0 (default)",
      "initial_duty_cycles": {
        "U": 0.25,
        "V": 0.5,
        "W": 0.75
      },
      "duty_step": 0.1,
      "duty_wrap_range": [
        0.0,
        1.0
      ],
      "update_interval_ms": 500,
      "min_pulse_time_s": 1e-06,
      "dead_time_s": 0.0,
      "notes": [
        "Center-aligned (up/down) PWM on TOM1; use synchronous shadow transfer for glitch-free updates.",
        "With complementary_mode=false, drive only HS channels (CH2/4/6)."
      ]
    },
    "device_configuration": {
      "target_device_macro": "DEVICE_TC38X",
      "pin_package": "IFX_PIN_PACKAGE_516",
      "device_family": "TC3xx",
      "clock_requirements": {
        "requires_xtal": true,
        "expected_system_freq_mhz": 300,
        "gtm_cmu_clock": "Configure CMU_FX clock for precise 20 kHz period on TOM1"
      }
    },
    "code_structure": {
      "file_pattern": "reference",
      "expected_files": [
        "GTM_TOM_3_Phase_Inverter_PWM.c",
        "GTM_TOM_3_Phase_Inverter_PWM.h"
      ],
      "has_cpu_files": true
    },
    "reference_context": {
      "includes_used": [
        "Ifx_Types.h",
        "IfxCpu.h",
        "IfxScuWdt.h",
        "Bsp.h",
        "GTM_TOM_3_Phase_Inverter_PWM.h",
        "Ifx_Cfg_Ssw.h",
        "IfxGtm_Tom_PwmHl.h",
        "IfxGtm_cfg_TC38x.h"
      ],
      "function_patterns": [
        "initGtmTom3phInv",
        "updateGtmTom3phInvDuty"
      ],
      "peripheral_usage": {
        "GTM_TOM": "3-phase PWM generation on TOM1",
        "Port": "Pin configuration for P00.[2..7]",
        "Watchdog": "Disable CPU and Safety watchdogs during init"
      }
    },
    "migration_numerical_values": {
      "DUTY_25_PERCENT": {
        "value": 25.0,
        "unit": "%",
        "label": "Phase U initial duty cycle"
      },
      "DUTY_50_PERCENT": {
        "value": 50.0,
        "unit": "%",
        "label": "Phase V initial duty cycle"
      },
      "DUTY_75_PERCENT": {
        "value": 75.0,
        "unit": "%",
        "label": "Phase W initial duty cycle"
      },
      "DUTY_STEP": {
        "value": 10.0,
        "unit": "%",
        "label": "Duty cycle step increment"
      },
      "DUTY_MIN": {
        "value": 10.0,
        "unit": "%",
        "label": "Minimum duty cycle"
      },
      "DUTY_MAX": {
        "value": 90.0,
        "unit": "%",
        "label": "Maximum duty cycle"
      },
      "PWM_FREQ_HZ": {
        "value": 20000.0,
        "unit": "Hz",
        "label": "PWM switching frequency"
      },
      "WAIT_TIME": {
        "value": 10.0,
        "unit": "ms",
        "label": "Wait / delay time"
      },
      "PWM_DEAD_TIME": {
        "value": 1e-06,
        "unit": "s",
        "label": "Dead-time between complementary outputs"
      },
      "PWM_MIN_PULSE_TIME": {
        "value": 1e-06,
        "unit": "s",
        "label": "Minimum pulse width"
      }
    },
    "template_compatibility": {
      "validated": true,
      "supported_peripherals": [
        "PWM",
        "GTM",
        "ETHERNET"
      ],
      "suggested_drivers": {
        "PWM": [
          "IfxGtm_Tom_Pwm"
        ],
        "GTM": [
          "IfxGtm_Tom_Pwm"
        ],
        "ETHERNET": [
          "IfxGeth_cfg_TC33xED",
          "IfxGeth_cfg_TC35x",
          "IfxGeth_cfg_TC38EVOx",
          "IfxGeth_cfg_TC38x",
          "IfxGeth_cfg_TC39xB",
          "IfxGeth_cfg_TC37x",
          "IfxGeth",
          "IfxGeth_Eth",
          "IfxGeth_cfg_TC37xED",
          "IfxGeth_cfg_TC36x"
        ],
        "_driver_selection": {
          "explicit_target": "IfxGtm_Tom_Pwm",
          "replaced_source": "IfxGtm_Tom_PwmHl",
          "primary_drivers": [
            "IfxGtm_Tom_Pwm"
          ],
          "avoid_drivers": [
            "IfxGtm_Tom_PwmHl"
          ]
        }
      },
      "warnings": []
    },
    "header_documentation_available": true,
    "config_values_extracted": 16
  },
  "hardware": {
    "microcontroller": {
      "model": "TC387QP",
      "verified": true
    },
    "peripheral_instance": {
      "module": "TOM1",
      "channels": [
        5,
        6,
        7,
        8,
        9,
        10
      ]
    },
    "pin_assignments": [
      {
        "signal": "U_LS",
        "port_pin": "P00.2",
        "function": "TOUT11",
        "pin_macro": "IfxGtm_TOM1_5_TOUT11_P00_2_OUT",
        "is_complementary": true,
        "verified": true,
        "source": "hardware_verified"
      },
      {
        "signal": "U_HS",
        "port_pin": "P00.3",
        "function": "TOUT12",
        "pin_macro": "IfxGtm_TOM1_2_TOUT12_P00_3_OUT",
        "is_complementary": false,
        "verified": true,
        "source": "hardware_verified",
        "_original_pin_macro": "IfxGtm_TOM1_6_TOUT12_P00_3_OUT"
      },
      {
        "signal": "V_LS",
        "port_pin": "P00.4",
        "function": "TOUT13",
        "pin_macro": "IfxGtm_TOM1_3_TOUT13_P00_4_OUT",
        "is_complementary": true,
        "verified": true,
        "source": "hardware_verified",
        "_original_pin_macro": "IfxGtm_TOM1_7_TOUT13_P00_4_OUT"
      },
      {
        "signal": "V_HS",
        "port_pin": "P00.5",
        "function": "TOUT14",
        "pin_macro": "IfxGtm_TOM1_1N_TOUT14_P00_5_OUT",
        "is_complementary": false,
        "verified": true,
        "source": "hardware_verified",
        "_original_pin_macro": "IfxGtm_TOM1_8_TOUT14_P00_5_OUT"
      },
      {
        "signal": "W_LS",
        "port_pin": "P00.6",
        "function": "TOUT15",
        "pin_macro": "IfxGtm_TOM1_2N_TOUT15_P00_6_OUT",
        "is_complementary": true,
        "verified": true,
        "source": "hardware_verified",
        "_original_pin_macro": "IfxGtm_TOM1_9_TOUT15_P00_6_OUT"
      },
      {
        "signal": "W_HS",
        "port_pin": "P00.7",
        "function": "TOUT16",
        "pin_macro": "IfxGtm_TOM1_3N_TOUT16_P00_7_OUT",
        "is_complementary": false,
        "verified": true,
        "source": "hardware_verified",
        "_original_pin_macro": "IfxGtm_TOM1_10_TOUT16_P00_7_OUT"
      }
    ],
    "clock_configuration": {
      "xtal_frequency_mhz": 20,
      "system_frequency_mhz": 300
    },
    "validation": {
      "all_verified": true,
      "conflicts": [],
      "reference_pins_valid": true
    },
    "template_validation": {
      "supported_peripherals": [
        "PWM",
        "GTM",
        "ETHERNET"
      ],
      "suggested_drivers": {
        "PWM": [
          "IfxGtm_Tom_Pwm"
        ],
        "GTM": [
          "IfxGtm_Tom_Pwm"
        ],
        "ETHERNET": [
          "IfxGeth_cfg_TC33xED",
          "IfxGeth_cfg_TC35x",
          "IfxGeth_cfg_TC38EVOx",
          "IfxGeth_cfg_TC38x",
          "IfxGeth_cfg_TC39xB",
          "IfxGeth_cfg_TC37x",
          "IfxGeth",
          "IfxGeth_Eth",
          "IfxGeth_cfg_TC37xED",
          "IfxGeth_cfg_TC36x"
        ],
        "_driver_selection": {
          "explicit_target": "IfxGtm_Tom_Pwm",
          "replaced_source": "IfxGtm_Tom_PwmHl",
          "primary_drivers": [
            "IfxGtm_Tom_Pwm"
          ],
          "avoid_drivers": [
            "IfxGtm_Tom_PwmHl"
          ]
        }
      },
      "warnings": []
    }
  }
}