{
  "error": "TDD code generation failed",
  "tdd_approach": true,
  "failed_phase": "production_code",
  "attempt": 5,
  "errors": [
    "Failed to generate working code after all retries"
  ],
  "warnings": [],
  "partial_results": {
    "mock_files": [
      "Ifx_Types.h",
      "Ifx_Types.c",
      "IfxPort.h",
      "IfxPort.c",
      "IfxEgtm_Pwm.h",
      "IfxEgtm_Pwm.c",
      "IfxEgtm_Dtm.h",
      "IfxEgtm_Dtm.c",
      "IfxEgtm.h",
      "IfxEgtm.c",
      "IfxEgtm_Cmu.h",
      "IfxEgtm_Cmu.c",
      "ifxsrc.h",
      "ifxsrc.c",
      "ifxegtm_pinmap.h",
      "ifxegtm_pinmap.c",
      "IfxStm.h",
      "IfxStm.c",
      "ifxegtm_atom.h",
      "ifxegtm_atom.c",
      "ifxport.h",
      "ifxport.c"
    ],
    "test_files": [
      "test_EGTM_ATOM_3_Phase_Inverter_PWM.c"
    ],
    "production_files": []
  },
  "mock_file_contents": {
    "Ifx_Types.h": "/**\n * \\file Ifx_Types.h\n * \\brief This files defines all types used by the IFX HAL and libraries\n *\n * \\version iLLD_1_20_0\n * \\copyright Copyright (c) 2024 Infineon Technologies AG. All rights reserved.\n *\n *\n *                                 IMPORTANT NOTICE\n *\n * Use of this file is subject to the terms of use agreed between (i) you or\n * the company in which ordinary course of business you are acting and (ii)\n * Infineon Technologies AG or its licensees. If and as long as no such terms\n * of use are agreed, use of this file is subject to following:\n *\n * Boost Software License - Version 1.0 - August 17th, 2003\n *\n * Permission is hereby granted, free of charge, to any person or organization\n * obtaining a copy of the software and accompanying documentation covered by\n * this license (the \"Software\") to use, reproduce, display, distribute,\n * execute, and transmit the Software, and to prepare derivative works of the\n * Software, and to permit third-parties to whom the Software is furnished to\n * do so, all subject to the following:\n *\n * The copyright notices in the Software and this entire statement, including\n * the above license grant, this restriction and the following disclaimer, must\n * be included in all copies of the Software, in whole or in part, and all\n * derivative works of the Software, unless such copies or derivative works are\n * solely in the form of machine-executable object code generated by a source\n * language processor.\n *\n * THE SOFTWARE IS PROVIDED \"AS IS\", WITHOUT WARRANTY OF ANY KIND, EXPRESS OR\n * IMPLIED, INCLUDING BUT NOT LIMITED TO THE WARRANTIES OF MERCHANTABILITY,\n * FITNESS FOR A PARTICULAR PURPOSE, TITLE AND NON-INFRINGEMENT. IN NO EVENT\n * SHALL THE COPYRIGHT HOLDERS OR ANYONE DISTRIBUTING THE SOFTWARE BE LIABLE\n * FOR ANY DAMAGES OR OTHER LIABILITY, WHETHER IN CONTRACT, TORT OR OTHERWISE,\n * ARISING FROM, OUT OF OR IN CONNECTION WITH THE SOFTWARE OR THE USE OR OTHER\n * DEALINGS IN THE SOFTWARE.\n *\n */\n\n#ifndef IFX_TYPES_H\n#define IFX_TYPES_H 1\n\n/* ============= BASIC TYPE DEFINITIONS FOR TDD ============= */\n/* These replace Platform_Types.h which has compiler dependencies */\ntypedef unsigned char       uint8;\ntypedef unsigned short      uint16;\ntypedef unsigned int        uint32;\ntypedef unsigned long long  uint64;\ntypedef signed char         sint8;\ntypedef signed short        sint16;\ntypedef signed int          sint32;\ntypedef signed long long    sint64;\ntypedef float               float32;\ntypedef double              float64;\ntypedef unsigned char       boolean;\n\n#ifndef TRUE\n#define TRUE  1\n#endif\n#ifndef FALSE\n#define FALSE 0\n#endif\n#ifndef NULL\n#define NULL ((void*)0)\n#endif\n\n/* Fractional types (for DSP operations) */\ntypedef sint16              fract;\ntypedef sint8               sfract;\n\n/* ============= END BASIC TYPE DEFINITIONS ============= */\n\n\n/******************************************************************************/\n/* mapping compiler specific keywords */\n/*******************************************************************************\n**                      Global Data Types                                     **\n**                      (Types not defined by AUTOSAR)                        **\n*******************************************************************************/\ntypedef const char        *pchar;                           /**< \\brief const char pointer                               */\ntypedef void              *pvoid;                           /**< \\brief void pointer                                     */\ntypedef volatile void     *vvoid;                           /**< \\brief volatile void pointer                            */\ntypedef void              (*voidfuncvoid) (void);           /**< \\brief void pointer which takes void argument           */\n\ntypedef struct\n{\n    float32 real;               /**< \\brief Real part */\n    float32 imag;               /**< \\brief Imaginary part */\n} cfloat32;\n\ntypedef struct\n{\n    sint32 real;\t\t\t\t/**< \\brief Real part */\n    sint32 imag;\t\t\t\t/**< \\brief Imaginary part */\n} csint32;\n\ntypedef struct\n{\n    sint16 real;\t\t\t\t/**< \\brief Real part */\n    sint16 imag;\t\t\t\t/**< \\brief Imaginary part */\n} csint16;\n\ntypedef sint64             Ifx_TickTime;    /**< \\brief Time in ticks */\n#define TIME_INFINITE ((Ifx_TickTime)0x7FFFFFFFFFFFFFFFLL)\n#define TIME_NULL     ((Ifx_TickTime)0x0000000000000000LL)\n\n#define IFX_ONES          (0xFFFFFFFFFFFFFFFFU)\n#define IFX_ZEROS         (0x0000000000000000U)\n\n\n#if CFG_LONG_SIZE_T\n#define IFX_SIZET_MAX (0x7FFFFFFFL)\ntypedef sint32 Ifx_SizeT;                       /**< \\brief Type used for data stream size */\n#else\n#define IFX_SIZET_MAX (0x7FFF)\ntypedef sint16 Ifx_SizeT;                       /**< \\brief Type used for data stream size */\n#endif\n\n/** \\brief Circular buffer definition. */\ntypedef struct\n{\n    void  *base;                   /**< \\brief buffer base address */\n    uint16 index;                  /**< \\brief buffer current index */\n    uint16 length;                 /**< \\brief buffer length*/\n} Ifx_CircularBuffer;\n\ntypedef uint16 Ifx_Priority;       /**< \\brief Used in interrupt service priorities */\ntypedef uint32 Ifx_TimerValue;     /**< \\brief Used in timer values */\ntypedef sint32 Ifx_SignedTimerVal; /**< \\brief Used in signed timer values */\n\ntypedef pvoid  Ifx_AddressValue;   /**< \\brief Used in address values */\n\n/** \\brief Signal active state definition. */\ntypedef enum\n{\n    Ifx_ActiveState_low  = 0,       /**< \\brief The signal is low active */\n    Ifx_ActiveState_high = 1        /**< \\brief The signal is high active */\n} Ifx_ActiveState;\n\n/**\n * Defines the PWM modes\n *\n * The 1st member shall start with value 0, and the next members value shall be the previous member +1\n * pwmMode_off shall be the member with the higher index\n * \\note enum order and values should not be modified, except Ifx_Pwm_Mode_init and Ifx_Pwm_Mode_count\n */\ntypedef enum\n{\n    Ifx_Pwm_Mode_centerAligned         = 0, /**< \\brief Center aligned mode */\n    Ifx_Pwm_Mode_centerAlignedInverted = 1, /**< \\brief Center aligned inverted aligned mode */\n    Ifx_Pwm_Mode_leftAligned           = 2, /**< \\brief Left aligned mode. The PWM period starts with a rising edge */\n    Ifx_Pwm_Mode_rightAligned          = 3, /**< \\brief Right aligned mode. The PWM period starts with a falling edge*/\n    Ifx_Pwm_Mode_off                   = 4, /**< \\brief All switch open */\n    Ifx_Pwm_Mode_init                  = 5, /**< \\brief Initialisation mode, do not use at run time */\n    Ifx_Pwm_Mode_count                      /**< \\brief Number of defined modes */\n} Ifx_Pwm_Mode;\n\n/** \\brief Module address and index map */\ntypedef struct\n{\n    volatile void *module;      /**< \\brief Module address */\n    sint32         index;       /**< \\brief Module index */\n} IfxModule_IndexMap;\n\n\n\n\ntypedef struct\n{\n    fract real;\t\t\t\t/**< \\brief Real part */\n    fract imag;\t\t\t\t/**< \\brief Imaginary part */\n} cfract;\n\ntypedef struct\n{\n    sfract real;\t\t\t\t/**< \\brief Real part */\n    sfract imag;\t\t\t\t/**< \\brief Imaginary part */\n} csfract;\n\n#define IFX_PI                  (3.1415926535897932384626433832795f)\n#define IFX_TWO_OVER_PI         (2.0 / IFX_PI)\n#define IFX_ONE_OVER_TWO_PI     (1.0f / (2.0f * IFX_PI))\n#define IFX_ONE_OVER_SQRT_THREE (0.57735026918962576450914878050196f)\n#define IFX_SQRT_TWO            (1.4142135623730950488016887242097f)\n#define IFX_SQRT_THREE          (1.7320508075688772935274463415059f)\n#define IFX_UNUSED_PARAMETER(x) if(x){}             /**< \\brief Added to handle warning resulting from cases where one/multiple function argument(s) is/are not used(but function signature maintained for legacy purposes). Another use case being usage of intrinsics wherein the compiler ignores it and copy pastes the statements using intrinsics directly to the object file and hence usage of arguments isn't visible to it.(eg: __mfcr() etc) */ \n\n\n/* ===== TDD MOCK MODULE INSTANCES ===== */\n\n/* ===== TDD MINIMAL ADDITIONS ===== */\n/* 2026-03-19: Only universally-needed macros that can't come from dynamic generation */\n\n/* NULL_PTR definition for iLLD compatibility */\n#ifndef NULL_PTR\n#define NULL_PTR ((void*)0)\n#endif\n\n\n\n#endif /* IFX_TYPES_H */\n",
    "Ifx_Types.c": "/* ifx_types.c - TDD stub for MODULE_* definitions */\n/* Auto-generated for TDD build - NO hardware register dependencies */\n#include \"illd_types/Ifx_Types.h\"\n\n/* ============================================================ */\n/* MODULE_* INSTANCE DEFINITIONS                                */\n/* These are stubs - real iLLD would link to hardware registers */\n/* ============================================================ */\n\n/* GTM/EGTM Module */\nIfx_GTM MODULE_GTM = {0};\nIfx_EGTM MODULE_EGTM = {0};\n\n/* STM Modules */\nIfx_STM MODULE_STM0 = {0};\nIfx_STM MODULE_STM1 = {0};\nIfx_STM MODULE_STM2 = {0};\n\n/* Port Modules - ALL common AURIX ports for generic support */\nIfx_P MODULE_P00 = {0};\nIfx_P MODULE_P01 = {0};\nIfx_P MODULE_P02 = {0};\nIfx_P MODULE_P03 = {0};  /* TC4D7 LED port */\nIfx_P MODULE_P04 = {0};\nIfx_P MODULE_P05 = {0};\nIfx_P MODULE_P06 = {0};\nIfx_P MODULE_P10 = {0};\nIfx_P MODULE_P11 = {0};\nIfx_P MODULE_P12 = {0};\nIfx_P MODULE_P13 = {0};  /* TC387 LED port */\nIfx_P MODULE_P14 = {0};\nIfx_P MODULE_P15 = {0};\nIfx_P MODULE_P20 = {0};  /* TC4D7 PWM port */\nIfx_P MODULE_P21 = {0};\nIfx_P MODULE_P22 = {0};\nIfx_P MODULE_P23 = {0};\nIfx_P MODULE_P32 = {0};\nIfx_P MODULE_P33 = {0};\nIfx_P MODULE_P34 = {0};\nIfx_P MODULE_P40 = {0};\n\n/* SCU Module */\nIfx_SCU MODULE_SCU = {0};\n",
    "IfxPort.h": "#ifndef IFXPORT_H\n#define IFXPORT_H\n\n#include \"illd_types/Ifx_Types.h\"  /* REQUIRED for uint8, uint16, uint32, boolean, float32 types */\n\n/* iLLD function declarations */\n/* Mock control: call counts */\n/* Mock control: return value for getPinState */\n/* Mock control: last-arg capture (value-carrying params) */\n/* Mock control: reset all state */\n/* ============= Function Declarations ============= */\n\n/* ============= Function Declarations ============= */\nvoid IfxPort_setPinModeOutput(Ifx_P *port, uint8 pinIndex, IfxPort_OutputMode mode, IfxPort_OutputIdx index);\nvoid IfxPort_setPinState(Ifx_P *port, uint8 pinIndex, IfxPort_State action);\nboolean IfxPort_getPinState(Ifx_P *port, uint8 pinIndex);\nvoid IfxPort_setPinHigh(Ifx_P *port, uint8 pinIndex);\nvoid IfxPort_setPinLow(Ifx_P *port, uint8 pinIndex);\nvoid IfxPort_setPinModeInput(Ifx_P *port, uint8 pinIndex, IfxPort_InputMode mode);\nvoid IfxPort_togglePin(Ifx_P *port, uint8 pinIndex);\nvoid IfxPort_setPinMode(Ifx_P *port, uint8 pinIndex, IfxPort_Mode mode);\nvoid IfxPort_setPinModeLVDS(Ifx_P *port, uint8 pinIndex, IfxPort_Mode pinMode, IfxPort_LvdsConfig *lvds);\nvoid IfxPort_setPinModex(Ifx_P *port, uint8 pinIndex, IfxPort_Modex modex);\nuint32 IfxPort_Mock_GetCallCount_setPinModeOutput(void);\nuint32 IfxPort_Mock_GetCallCount_setPinState(void);\nuint32 IfxPort_Mock_GetCallCount_getPinState(void);\nuint32 IfxPort_Mock_GetCallCount_setPinHigh(void);\nuint32 IfxPort_Mock_GetCallCount_setPinLow(void);\nuint32 IfxPort_Mock_GetCallCount_setPinModeInput(void);\nuint32 IfxPort_Mock_GetCallCount_togglePin(void);\nuint32 IfxPort_Mock_GetCallCount_setPinMode(void);\nuint32 IfxPort_Mock_GetCallCount_setPinModeLVDS(void);\nuint32 IfxPort_Mock_GetCallCount_setPinModex(void);\nvoid    IfxPort_Mock_SetReturn_getPinState(boolean value);\nboolean IfxPort_Mock_GetReturn_getPinState(void);\nuint8   IfxPort_Mock_GetLastArg_setPinModeOutput_pinIndex(void);\nuint32  IfxPort_Mock_GetLastArg_setPinModeOutput_mode(void);\nuint32  IfxPort_Mock_GetLastArg_setPinModeOutput_index(void);\nuint8   IfxPort_Mock_GetLastArg_setPinState_pinIndex(void);\nuint32  IfxPort_Mock_GetLastArg_setPinState_action(void);\nuint8   IfxPort_Mock_GetLastArg_getPinState_pinIndex(void);\nuint8   IfxPort_Mock_GetLastArg_setPinHigh_pinIndex(void);\nuint8   IfxPort_Mock_GetLastArg_setPinLow_pinIndex(void);\nuint8   IfxPort_Mock_GetLastArg_setPinModeInput_pinIndex(void);\nuint32  IfxPort_Mock_GetLastArg_setPinModeInput_mode(void);\nuint8   IfxPort_Mock_GetLastArg_togglePin_pinIndex(void);\nuint8   IfxPort_Mock_GetLastArg_setPinMode_pinIndex(void);\nuint32  IfxPort_Mock_GetLastArg_setPinMode_mode(void);\nuint8   IfxPort_Mock_GetLastArg_setPinModeLVDS_pinIndex(void);\nuint32  IfxPort_Mock_GetLastArg_setPinModeLVDS_pinMode(void);\nuint8   IfxPort_Mock_GetLastArg_setPinModex_pinIndex(void);\nuint32  IfxPort_Mock_GetLastArg_setPinModex_modex(void);\nvoid IfxPort_Mock_Reset(void);\n\n#endif",
    "IfxPort.c": "\n/* Call counters */\nstatic uint32 s_setPinModeOutput_count = 0;\nstatic uint32 s_setPinState_count      = 0;\nstatic uint32 s_getPinState_count      = 0;\nstatic uint32 s_setPinHigh_count       = 0;\nstatic uint32 s_setPinLow_count        = 0;\nstatic uint32 s_setPinModeInput_count  = 0;\nstatic uint32 s_togglePin_count        = 0;\nstatic uint32 s_setPinMode_count       = 0;\nstatic uint32 s_setPinModeLVDS_count   = 0;\nstatic uint32 s_setPinModex_count      = 0;\n\n/* Return controls */\nstatic boolean s_getPinState_ret = FALSE;\n\n/* Last-arg captures */\nstatic uint8  s_setPinModeOutput_lastPinIndex = 0u;\nstatic uint32 s_setPinModeOutput_lastMode     = 0u;\nstatic uint32 s_setPinModeOutput_lastIndex    = 0u;\n\nstatic uint8  s_setPinState_lastPinIndex = 0u;\nstatic uint32 s_setPinState_lastAction   = 0u;\n\nstatic uint8  s_getPinState_lastPinIndex = 0u;\n\nstatic uint8  s_setPinHigh_lastPinIndex = 0u;\nstatic uint8  s_setPinLow_lastPinIndex  = 0u;\n\nstatic uint8  s_setPinModeInput_lastPinIndex = 0u;\nstatic uint32 s_setPinModeInput_lastMode     = 0u;\n\nstatic uint8  s_togglePin_lastPinIndex = 0u;\n\nstatic uint8  s_setPinMode_lastPinIndex = 0u;\nstatic uint32 s_setPinMode_lastMode     = 0u;\n\nstatic uint8  s_setPinModeLVDS_lastPinIndex = 0u;\nstatic uint32 s_setPinModeLVDS_lastPinMode  = 0u;\n\nstatic uint8  s_setPinModex_lastPinIndex = 0u;\nstatic uint32 s_setPinModex_lastModex    = 0u;\n\n/* Implementations */\nvoid IfxPort_setPinModeOutput(Ifx_P *port, uint8 pinIndex, IfxPort_OutputMode mode, IfxPort_OutputIdx index)\n{\n    (void)port;\n    s_setPinModeOutput_count++;\n    s_setPinModeOutput_lastPinIndex = pinIndex;\n    s_setPinModeOutput_lastMode     = (uint32)mode;\n    s_setPinModeOutput_lastIndex    = (uint32)index;\n}\n\nvoid IfxPort_setPinState(Ifx_P *port, uint8 pinIndex, IfxPort_State action)\n{\n    (void)port;\n    s_setPinState_count++;\n    s_setPinState_lastPinIndex = pinIndex;\n    s_setPinState_lastAction   = (uint32)action;\n}\n\nboolean IfxPort_getPinState(Ifx_P *port, uint8 pinIndex)\n{\n    (void)port;\n    s_getPinState_count++;\n    s_getPinState_lastPinIndex = pinIndex;\n    return s_getPinState_ret;\n}\n\nvoid IfxPort_setPinHigh(Ifx_P *port, uint8 pinIndex)\n{\n    (void)port;\n    s_setPinHigh_count++;\n    s_setPinHigh_lastPinIndex = pinIndex;\n}\n\nvoid IfxPort_setPinLow(Ifx_P *port, uint8 pinIndex)\n{\n    (void)port;\n    s_setPinLow_count++;\n    s_setPinLow_lastPinIndex = pinIndex;\n}\n\nvoid IfxPort_setPinModeInput(Ifx_P *port, uint8 pinIndex, IfxPort_InputMode mode)\n{\n    (void)port;\n    s_setPinModeInput_count++;\n    s_setPinModeInput_lastPinIndex = pinIndex;\n    s_setPinModeInput_lastMode     = (uint32)mode;\n}\n\nvoid IfxPort_togglePin(Ifx_P *port, uint8 pinIndex)\n{\n    (void)port;\n    s_togglePin_count++;\n    s_togglePin_lastPinIndex = pinIndex;\n}\n\nvoid IfxPort_setPinMode(Ifx_P *port, uint8 pinIndex, IfxPort_Mode mode)\n{\n    (void)port;\n    s_setPinMode_count++;\n    s_setPinMode_lastPinIndex = pinIndex;\n    s_setPinMode_lastMode     = (uint32)mode;\n}\n\nvoid IfxPort_setPinModeLVDS(Ifx_P *port, uint8 pinIndex, IfxPort_Mode pinMode, IfxPort_LvdsConfig *lvds)\n{\n    (void)port;\n    (void)lvds;\n    s_setPinModeLVDS_count++;\n    s_setPinModeLVDS_lastPinIndex = pinIndex;\n    s_setPinModeLVDS_lastPinMode  = (uint32)pinMode;\n}\n\nvoid IfxPort_setPinModex(Ifx_P *port, uint8 pinIndex, IfxPort_Modex modex)\n{\n    (void)port;\n    s_setPinModex_count++;\n    s_setPinModex_lastPinIndex = pinIndex;\n    s_setPinModex_lastModex    = (uint32)modex;\n}\n\n/* Mock control implementations */\nuint32 IfxPort_Mock_GetCallCount_setPinModeOutput(void) { return s_setPinModeOutput_count; }\nuint32 IfxPort_Mock_GetCallCount_setPinState(void)      { return s_setPinState_count; }\nuint32 IfxPort_Mock_GetCallCount_getPinState(void)      { return s_getPinState_count; }\nuint32 IfxPort_Mock_GetCallCount_setPinHigh(void)       { return s_setPinHigh_count; }\nuint32 IfxPort_Mock_GetCallCount_setPinLow(void)        { return s_setPinLow_count; }\nuint32 IfxPort_Mock_GetCallCount_setPinModeInput(void)  { return s_setPinModeInput_count; }\nuint32 IfxPort_Mock_GetCallCount_togglePin(void)        { return s_togglePin_count; }\nuint32 IfxPort_Mock_GetCallCount_setPinMode(void)       { return s_setPinMode_count; }\nuint32 IfxPort_Mock_GetCallCount_setPinModeLVDS(void)   { return s_setPinModeLVDS_count; }\nuint32 IfxPort_Mock_GetCallCount_setPinModex(void)      { return s_setPinModex_count; }\n\nvoid    IfxPort_Mock_SetReturn_getPinState(boolean value) { s_getPinState_ret = value; }\nboolean IfxPort_Mock_GetReturn_getPinState(void)         { return s_getPinState_ret; }\n\nuint8  IfxPort_Mock_GetLastArg_setPinModeOutput_pinIndex(void) { return s_setPinModeOutput_lastPinIndex; }\nuint32 IfxPort_Mock_GetLastArg_setPinModeOutput_mode(void)     { return s_setPinModeOutput_lastMode; }\nuint32 IfxPort_Mock_GetLastArg_setPinModeOutput_index(void)    { return s_setPinModeOutput_lastIndex; }\n\nuint8  IfxPort_Mock_GetLastArg_setPinState_pinIndex(void) { return s_setPinState_lastPinIndex; }\nuint32 IfxPort_Mock_GetLastArg_setPinState_action(void)   { return s_setPinState_lastAction; }\n\nuint8  IfxPort_Mock_GetLastArg_getPinState_pinIndex(void) { return s_getPinState_lastPinIndex; }\n\nuint8  IfxPort_Mock_GetLastArg_setPinHigh_pinIndex(void)  { return s_setPinHigh_lastPinIndex; }\nuint8  IfxPort_Mock_GetLastArg_setPinLow_pinIndex(void)   { return s_setPinLow_lastPinIndex; }\n\nuint8  IfxPort_Mock_GetLastArg_setPinModeInput_pinIndex(void) { return s_setPinModeInput_lastPinIndex; }\nuint32 IfxPort_Mock_GetLastArg_setPinModeInput_mode(void)     { return s_setPinModeInput_lastMode; }\n\nuint8  IfxPort_Mock_GetLastArg_togglePin_pinIndex(void)   { return s_togglePin_lastPinIndex; }\n\nuint8  IfxPort_Mock_GetLastArg_setPinMode_pinIndex(void)  { return s_setPinMode_lastPinIndex; }\nuint32 IfxPort_Mock_GetLastArg_setPinMode_mode(void)      { return s_setPinMode_lastMode; }\n\nuint8  IfxPort_Mock_GetLastArg_setPinModeLVDS_pinIndex(void) { return s_setPinModeLVDS_lastPinIndex; }\nuint32 IfxPort_Mock_GetLastArg_setPinModeLVDS_pinMode(void)  { return s_setPinModeLVDS_lastPinMode; }\n\nuint8  IfxPort_Mock_GetLastArg_setPinModex_pinIndex(void) { return s_setPinModex_lastPinIndex; }\nuint32 IfxPort_Mock_GetLastArg_setPinModex_modex(void)    { return s_setPinModex_lastModex; }\n\nvoid IfxPort_Mock_Reset(void)\n{\n    s_setPinModeOutput_count = 0u;\n    s_setPinState_count      = 0u;\n    s_getPinState_count      = 0u;\n    s_setPinHigh_count       = 0u;\n    s_setPinLow_count        = 0u;\n    s_setPinModeInput_count  = 0u;\n    s_togglePin_count        = 0u;\n    s_setPinMode_count       = 0u;\n    s_setPinModeLVDS_count   = 0u;\n    s_setPinModex_count      = 0u;\n\n    s_getPinState_ret = FALSE;\n\n    s_setPinModeOutput_lastPinIndex = 0u;\n    s_setPinModeOutput_lastMode     = 0u;\n    s_setPinModeOutput_lastIndex    = 0u;\n\n    s_setPinState_lastPinIndex = 0u;\n    s_setPinState_lastAction   = 0u;\n\n    s_getPinState_lastPinIndex = 0u;\n\n    s_setPinHigh_lastPinIndex = 0u;\n    s_setPinLow_lastPinIndex  = 0u;\n\n    s_setPinModeInput_lastPinIndex = 0u;\n    s_setPinModeInput_lastMode     = 0u;\n\n    s_togglePin_lastPinIndex = 0u;\n\n    s_setPinMode_lastPinIndex = 0u;\n    s_setPinMode_lastMode     = 0u;\n\n    s_setPinModeLVDS_lastPinIndex = 0u;\n    s_setPinModeLVDS_lastPinMode  = 0u;\n\n    s_setPinModex_lastPinIndex = 0u;\n    s_setPinModex_lastModex    = 0u;\n}\n",
    "IfxEgtm_Pwm.h": "#ifndef IFXEGTM_PWM_H\n#define IFXEGTM_PWM_H\n\n#include \"illd_types/Ifx_Types.h\"  /* REQUIRED for uint8, uint16, uint32, boolean, float32 types */\n\n/* iLLD function declarations */\n/* Mock control: call counts */\n/* Mock control: array value capture for updateChannelsDutyImmediate */\n/* Mock control: reset all state */\n/* ============= Function Declarations ============= */\n\n/* ============= Function Declarations ============= */\nvoid IfxEgtm_Pwm_init(IfxEgtm_Pwm *pwm, IfxEgtm_Pwm_Channel *channels, IfxEgtm_Pwm_Config *config);\nvoid IfxEgtm_Pwm_startSyncedChannels(IfxEgtm_Pwm *pwm);\nvoid IfxEgtm_Pwm_updateChannelsDutyImmediate(IfxEgtm_Pwm *pwm, float32 *requestDuty);\nvoid IfxEgtm_Pwm_initConfig(IfxEgtm_Pwm_Config *config, Ifx_EGTM *egtmSFR);\nuint32 IfxEgtm_Pwm_Mock_GetCallCount_init(void);\nuint32 IfxEgtm_Pwm_Mock_GetCallCount_startSyncedChannels(void);\nuint32 IfxEgtm_Pwm_Mock_GetCallCount_updateChannelsDutyImmediate(void);\nuint32 IfxEgtm_Pwm_Mock_GetCallCount_initConfig(void);\nfloat32 IfxEgtm_Pwm_Mock_GetLastArrayArg_updateDuty(uint32 index);\nfloat32 IfxEgtm_Pwm_Mock_GetArgHistory_updateDuty(uint32 callIdx, uint32 elemIdx);\nuint32  IfxEgtm_Pwm_Mock_GetArgHistoryCount_updateDuty(void);\nvoid IfxEgtm_Pwm_Mock_Reset(void);\n\n#endif",
    "IfxEgtm_Pwm.c": "\n/* Call counters */\nstatic uint32 s_init_count                     = 0u;\nstatic uint32 s_startSyncedChannels_count      = 0u;\nstatic uint32 s_updateChannelsDutyImmediate_count = 0u;\nstatic uint32 s_initConfig_count               = 0u;\n\n/* Array capture configuration */\n#define IFXEGTM_PWM_MOCK_MAX_ELEMENTS 8u\n#define IFXEGTM_PWM_MOCK_MAX_HISTORY  32u\n\nstatic float32 s_updateDuty_lastArray[IFXEGTM_PWM_MOCK_MAX_ELEMENTS] = {0};\nstatic float32 s_updateDuty_history[IFXEGTM_PWM_MOCK_MAX_HISTORY][IFXEGTM_PWM_MOCK_MAX_ELEMENTS] = {{0}};\nstatic uint32  s_updateDuty_historyCount = 0u;\n\n/* Implementations */\nvoid IfxEgtm_Pwm_init(IfxEgtm_Pwm *pwm, IfxEgtm_Pwm_Channel *channels, IfxEgtm_Pwm_Config *config)\n{\n    (void)pwm;\n    (void)channels;\n    (void)config; /* Exception Pattern D not applied due to opaque config in mock */\n    s_init_count++;\n}\n\nvoid IfxEgtm_Pwm_startSyncedChannels(IfxEgtm_Pwm *pwm)\n{\n    (void)pwm;\n    s_startSyncedChannels_count++;\n}\n\nvoid IfxEgtm_Pwm_updateChannelsDutyImmediate(IfxEgtm_Pwm *pwm, float32 *requestDuty)\n{\n    (void)pwm;\n    s_updateChannelsDutyImmediate_count++;\n    if (requestDuty != NULL_PTR)\n    {\n        uint32 i;\n        for (i = 0u; i < IFXEGTM_PWM_MOCK_MAX_ELEMENTS; i++)\n        {\n            s_updateDuty_lastArray[i] = requestDuty[i];\n        }\n        if (s_updateDuty_historyCount < IFXEGTM_PWM_MOCK_MAX_HISTORY)\n        {\n            uint32 j;\n            for (j = 0u; j < IFXEGTM_PWM_MOCK_MAX_ELEMENTS; j++)\n            {\n                s_updateDuty_history[s_updateDuty_historyCount][j] = requestDuty[j];\n            }\n            s_updateDuty_historyCount++;\n        }\n    }\n}\n\nvoid IfxEgtm_Pwm_initConfig(IfxEgtm_Pwm_Config *config, Ifx_EGTM *egtmSFR)\n{\n    (void)config;\n    (void)egtmSFR;\n    s_initConfig_count++;\n}\n\n/* Mock control implementations */\nuint32 IfxEgtm_Pwm_Mock_GetCallCount_init(void) { return s_init_count; }\nuint32 IfxEgtm_Pwm_Mock_GetCallCount_startSyncedChannels(void) { return s_startSyncedChannels_count; }\nuint32 IfxEgtm_Pwm_Mock_GetCallCount_updateChannelsDutyImmediate(void) { return s_updateChannelsDutyImmediate_count; }\nuint32 IfxEgtm_Pwm_Mock_GetCallCount_initConfig(void) { return s_initConfig_count; }\n\nfloat32 IfxEgtm_Pwm_Mock_GetLastArrayArg_updateDuty(uint32 index)\n{\n    if (index < IFXEGTM_PWM_MOCK_MAX_ELEMENTS)\n    {\n        return s_updateDuty_lastArray[index];\n    }\n    return 0.0f;\n}\n\nfloat32 IfxEgtm_Pwm_Mock_GetArgHistory_updateDuty(uint32 callIdx, uint32 elemIdx)\n{\n    if ((callIdx < IFXEGTM_PWM_MOCK_MAX_HISTORY) && (elemIdx < IFXEGTM_PWM_MOCK_MAX_ELEMENTS))\n    {\n        return s_updateDuty_history[callIdx][elemIdx];\n    }\n    return 0.0f;\n}\n\nuint32 IfxEgtm_Pwm_Mock_GetArgHistoryCount_updateDuty(void)\n{\n    return s_updateDuty_historyCount;\n}\n\nvoid IfxEgtm_Pwm_Mock_Reset(void)\n{\n    uint32 i, j;\n    s_init_count = 0u;\n    s_startSyncedChannels_count = 0u;\n    s_updateChannelsDutyImmediate_count = 0u;\n    s_initConfig_count = 0u;\n\n    for (i = 0u; i < IFXEGTM_PWM_MOCK_MAX_ELEMENTS; i++)\n    {\n        s_updateDuty_lastArray[i] = 0.0f;\n    }\n    for (i = 0u; i < IFXEGTM_PWM_MOCK_MAX_HISTORY; i++)\n    {\n        for (j = 0u; j < IFXEGTM_PWM_MOCK_MAX_ELEMENTS; j++)\n        {\n            s_updateDuty_history[i][j] = 0.0f;\n        }\n    }\n    s_updateDuty_historyCount = 0u;\n}\n",
    "IfxEgtm_Dtm.h": "#ifndef IFXEGTM_DTM_H\n#define IFXEGTM_DTM_H\n\n#include \"illd_types/Ifx_Types.h\"  /* REQUIRED for uint8, uint16, uint32, boolean, float32 types */\n\n/* iLLD function declarations */\n/* Mock control: call counts */\n/* Mock control: last-arg capture */\n/* Mock control: reset */\n/* ============= Function Declarations ============= */\n\n/* ============= Function Declarations ============= */\nvoid IfxEgtm_Dtm_setClockSource(Ifx_EGTM_CLS_CDTM_DTM *dtm, IfxEgtm_Dtm_ClockSource clockSource);\nuint32 IfxEgtm_Dtm_Mock_GetCallCount_setClockSource(void);\nuint32 IfxEgtm_Dtm_Mock_GetLastArg_setClockSource(void);\nvoid IfxEgtm_Dtm_Mock_Reset(void);\n\n#endif",
    "IfxEgtm_Dtm.c": "\nstatic uint32 s_setClockSource_count = 0u;\nstatic uint32 s_setClockSource_last  = 0u;\n\nvoid IfxEgtm_Dtm_setClockSource(Ifx_EGTM_CLS_CDTM_DTM *dtm, IfxEgtm_Dtm_ClockSource clockSource)\n{\n    (void)dtm;\n    s_setClockSource_count++;\n    s_setClockSource_last = (uint32)clockSource;\n}\n\nuint32 IfxEgtm_Dtm_Mock_GetCallCount_setClockSource(void)\n{\n    return s_setClockSource_count;\n}\n\nuint32 IfxEgtm_Dtm_Mock_GetLastArg_setClockSource(void)\n{\n    return s_setClockSource_last;\n}\n\nvoid IfxEgtm_Dtm_Mock_Reset(void)\n{\n    s_setClockSource_count = 0u;\n    s_setClockSource_last  = 0u;\n}\n",
    "IfxEgtm.h": "#ifndef IFXEGTM_H\n#define IFXEGTM_H\n\n#include \"illd_types/Ifx_Types.h\"  /* REQUIRED for uint8, uint16, uint32, boolean, float32 types */\n\n/* iLLD function declarations */\n/* Mock control: call counts */\n/* Mock control: reset */\n/* EGTM enable/disable functions (auto-injected for TDD) */\n/* ============= Function Declarations ============= */\n\n/* ============= Function Declarations ============= */\nvoid IfxEgtm_enable(Ifx_EGTM *egtm);\nuint32 IfxEgtm_Mock_GetCallCount_enable(void);\nvoid IfxEgtm_Mock_Reset(void);\nvoid IfxEgtm_enable(Ifx_EGTM *egtm);\nboolean IfxEgtm_isEnabled(Ifx_EGTM *egtm);\n\n#endif",
    "IfxEgtm.c": "\nstatic uint32 s_enable_count = 0u;\n\n/* Replaced by stateful mock below */\n\n\n\n\n\n/* Stateful EGTM enable mock (auto-injected for TDD) */\nstatic uint32 s_egtm_enable_count = 0;\nstatic boolean s_egtm_enabled = FALSE;\n\nvoid IfxEgtm_enable(Ifx_EGTM *egtm) {\n    (void)egtm;\n    s_egtm_enable_count++;\n    s_egtm_enabled = TRUE;\n}\n\nboolean IfxEgtm_isEnabled(Ifx_EGTM *egtm) {\n    (void)egtm;\n    return s_egtm_enabled;\n}\n\nuint32 IfxEgtm_Mock_GetCallCount_enable(void) { return s_egtm_enable_count; }\n\nvoid IfxEgtm_Mock_Reset(void) {\n    s_egtm_enable_count = 0;\n    s_egtm_enabled = FALSE;\n}\n",
    "IfxEgtm_Cmu.h": "#ifndef IFXEGTM_CMU_H\n#define IFXEGTM_CMU_H\n\n#include \"illd_types/Ifx_Types.h\"  /* REQUIRED for uint8, uint16, uint32, boolean, float32 types */\n\n/* iLLD function declarations */\n/* Mock control: call counts */\n/* Mock control: last-arg capture */\n/* Mock control: reset */\n/* EGTM CMU Clock Enable Macros (auto-injected for TDD) */\n#define IFXEGTM_CMU_CLKEN_CLK0   (1U << 0)\n#define IFXEGTM_CMU_CLKEN_CLK1   (1U << 1)\n#define IFXEGTM_CMU_CLKEN_CLK2   (1U << 2)\n#define IFXEGTM_CMU_CLKEN_CLK3   (1U << 3)\n#define IFXEGTM_CMU_CLKEN_CLK4   (1U << 4)\n#define IFXEGTM_CMU_CLKEN_CLK5   (1U << 5)\n#define IFXEGTM_CMU_CLKEN_CLK6   (1U << 6)\n#define IFXEGTM_CMU_CLKEN_CLK7   (1U << 7)\n#define IFXEGTM_CMU_CLKEN_FXCLK  (1U << 8)\n#define IFXEGTM_CMU_CLKEN_ALL    (0x1FFU)\n/* EGTM CMU frequency functions (auto-injected for TDD) */\n/* ============= Function Declarations ============= */\n\n/* ============= Function Declarations ============= */\nvoid IfxEgtm_Cmu_enableClocks(Ifx_EGTM *egtm, uint32 clkMask);\nuint32 IfxEgtm_Cmu_Mock_GetCallCount_enableClocks(void);\nuint32 IfxEgtm_Cmu_Mock_GetLastArg_enableClocks_clkMask(void);\nvoid IfxEgtm_Cmu_Mock_Reset(void);\nfloat32 IfxEgtm_Cmu_getGclkFrequency(Ifx_EGTM *egtm);\nfloat32 IfxEgtm_Cmu_getModuleFrequency(Ifx_EGTM *egtm);\nvoid IfxEgtm_Cmu_setGclkFrequency(Ifx_EGTM *egtm, float32 frequency);\nvoid IfxEgtm_Cmu_enableClocks(Ifx_EGTM *egtm, uint32 clkMask);\n\n#endif",
    "IfxEgtm_Cmu.c": "\nstatic uint32 s_enableClocks_count   = 0u;\nstatic uint32 s_enableClocks_clkMask = 0u;\n\nvoid IfxEgtm_Cmu_enableClocks(Ifx_EGTM *egtm, uint32 clkMask)\n{\n    (void)egtm;\n    s_enableClocks_count++;\n    s_enableClocks_clkMask = clkMask;\n}\n\nuint32 IfxEgtm_Cmu_Mock_GetCallCount_enableClocks(void)\n{\n    return s_enableClocks_count;\n}\n\nuint32 IfxEgtm_Cmu_Mock_GetLastArg_enableClocks_clkMask(void)\n{\n    return s_enableClocks_clkMask;\n}\n\nvoid IfxEgtm_Cmu_Mock_Reset(void)\n{\n    s_enableClocks_count   = 0u;\n    s_enableClocks_clkMask = 0u;\n}\n",
    "ifxsrc.h": "#ifndef IFXSRC_H\n#define IFXSRC_H\n\n#include \"illd_types/Ifx_Types.h\"\n\n/* ============= Type Definitions ============= */\n/* Ifx_SRC_SRCR - defined in Ifx_Types.h */\n/* IfxSrc_Tos - from illd_types/Ifx_Types.h */\n\n/* Service Request Control Register stub */\n/* Type of Service enum for interrupt routing */\n\n/* ============= Function Declarations ============= */\nvoid IfxSrc_clearOverrun(volatile Ifx_SRC_SRCR *src);\nvoid IfxSrc_clearRequest(volatile Ifx_SRC_SRCR *src);\nboolean IfxSrc_isOverrun(volatile Ifx_SRC_SRCR *src);\nboolean IfxSrc_isRequested(volatile Ifx_SRC_SRCR *src);\nvoid IfxSrc_setRequest(volatile Ifx_SRC_SRCR *src);\nboolean IfxSrc_getEccError(volatile Ifx_INT *intr, IfxSrc_Tos typeOfService);\nvoid IfxSrc_clearEccError(volatile Ifx_INT *intr, IfxSrc_Tos typeOfService);\nvoid IfxSrc_enableBroadcastInterruptLine(volatile Ifx_INT *intr, IfxSrc_Int_group groupNum, uint8 interruptLine);\nvoid IfxSrc_disableBroadcastInterruptLine(volatile Ifx_INT *intr, IfxSrc_Int_group groupNum, uint8 interruptLine);\nvoid IfxSrc_triggerBroadcastinterruptLine(volatile Ifx_INT *intr, IfxSrc_Int_group groupNum, uint8 interruptLine);\nvoid IfxSrc_triggerBroadcastinterrupts(volatile Ifx_INT *intr, IfxSrc_Int_group groupNum, uint8 interrupts);\nvoid IfxSrc_deinit(volatile Ifx_SRC_SRCR *src);\nvoid IfxSrc_disable(volatile Ifx_SRC_SRCR *src);\nvoid IfxSrc_enable(volatile Ifx_SRC_SRCR *src);\nvoid IfxSrc_init(volatile Ifx_SRC_SRCR *src, IfxSrc_Tos typOfService, Ifx_Priority priority, IfxSrc_VmId vmNumber);\nvoid IfxSrc_configOtgbTriggerSet(volatile Ifx_INT *intr, IfxSrc_TrigSet triggerSelection);\nvoid IfxSrc_configOtgbBusSelect(volatile Ifx_INT *intr, IfxSrc_OtgbBusSel busSelection);\nvoid IfxSrc_updateGpsrData(volatile Ifx_INT_GPSRG_SWC *src, uint16 data);\nvoid IfxSrc_setOtgbSrnIndex(volatile Ifx_INT *intr, IfxSrc_OtgbSrnIndex srnIndex, IfxSrc_OtgbSrnIndexVal *srnIndexVal);\nvoid IfxSrc_initOtgb(volatile Ifx_INT *intr, IfxSrc_OtgbConfig *OtgbConfig);\nvoid IfxSrc_initOtgbConfig(IfxSrc_OtgbConfig *OtgbConfig);\nvoid IfxSrc_configOtgbServiceProviderTrigger(volatile Ifx_INT *intr, IfxSrc_spConfig *spConfig);\nvoid IfxSrc_configureAccessToSrcs(IfxApApu_ApuConfig *apConfig);\n\n#endif /* IFXSRC_H */",
    "ifxsrc.c": "\nvoid IfxSrc_clearOverrun(volatile Ifx_SRC_SRCR *src) {\n    (void)src; /* Unused in mock */\n}\n\nvoid IfxSrc_clearRequest(volatile Ifx_SRC_SRCR *src) {\n    (void)src; /* Unused in mock */\n}\n\nboolean IfxSrc_isOverrun(volatile Ifx_SRC_SRCR *src) {\n    (void)src;\n    return TRUE; /* Stub always succeeds */\n}\n\nboolean IfxSrc_isRequested(volatile Ifx_SRC_SRCR *src) {\n    (void)src;\n    return TRUE; /* Stub always succeeds */\n}\n\nvoid IfxSrc_setRequest(volatile Ifx_SRC_SRCR *src) {\n    (void)src; /* Unused in mock */\n}\n\nboolean IfxSrc_getEccError(volatile Ifx_INT *intr, IfxSrc_Tos typeOfService) {\n    (void)intr;\n    (void)typeOfService;\n    return TRUE; /* Stub always succeeds */\n}\n\nvoid IfxSrc_clearEccError(volatile Ifx_INT *intr, IfxSrc_Tos typeOfService) {\n    (void)intr; /* Unused in mock */\n    (void)typeOfService; /* Unused in mock */\n}\n\nvoid IfxSrc_enableBroadcastInterruptLine(volatile Ifx_INT *intr, IfxSrc_Int_group groupNum, uint8 interruptLine) {\n    (void)intr; /* Unused in mock */\n    (void)groupNum; /* Unused in mock */\n    (void)interruptLine; /* Unused in mock */\n}\n\nvoid IfxSrc_disableBroadcastInterruptLine(volatile Ifx_INT *intr, IfxSrc_Int_group groupNum, uint8 interruptLine) {\n    (void)intr; /* Unused in mock */\n    (void)groupNum; /* Unused in mock */\n    (void)interruptLine; /* Unused in mock */\n}\n\nvoid IfxSrc_triggerBroadcastinterruptLine(volatile Ifx_INT *intr, IfxSrc_Int_group groupNum, uint8 interruptLine) {\n    (void)intr; /* Unused in mock */\n    (void)groupNum; /* Unused in mock */\n    (void)interruptLine; /* Unused in mock */\n}\n\nvoid IfxSrc_triggerBroadcastinterrupts(volatile Ifx_INT *intr, IfxSrc_Int_group groupNum, uint8 interrupts) {\n    (void)intr; /* Unused in mock */\n    (void)groupNum; /* Unused in mock */\n    (void)interrupts; /* Unused in mock */\n}\n\nvoid IfxSrc_deinit(volatile Ifx_SRC_SRCR *src) {\n    (void)src; /* Unused in mock */\n}\n\nvoid IfxSrc_disable(volatile Ifx_SRC_SRCR *src) {\n    (void)src; /* Unused in mock */\n}\n\nvoid IfxSrc_enable(volatile Ifx_SRC_SRCR *src) {\n    (void)src; /* Unused in mock */\n}\n\nvoid IfxSrc_init(volatile Ifx_SRC_SRCR *src, IfxSrc_Tos typOfService, Ifx_Priority priority, IfxSrc_VmId vmNumber) {\n    (void)src; /* Unused in mock */\n    (void)typOfService; /* Unused in mock */\n    (void)priority; /* Unused in mock */\n    (void)vmNumber; /* Unused in mock */\n}\n\nvoid IfxSrc_configOtgbTriggerSet(volatile Ifx_INT *intr, IfxSrc_TrigSet triggerSelection) {\n    (void)intr; /* Unused in mock */\n    (void)triggerSelection; /* Unused in mock */\n}\n\nvoid IfxSrc_configOtgbBusSelect(volatile Ifx_INT *intr, IfxSrc_OtgbBusSel busSelection) {\n    (void)intr; /* Unused in mock */\n    (void)busSelection; /* Unused in mock */\n}\n\nvoid IfxSrc_updateGpsrData(volatile Ifx_INT_GPSRG_SWC *src, uint16 data) {\n    (void)src; /* Unused in mock */\n    (void)data; /* Unused in mock */\n}\n\nvoid IfxSrc_setOtgbSrnIndex(volatile Ifx_INT *intr, IfxSrc_OtgbSrnIndex srnIndex, IfxSrc_OtgbSrnIndexVal *srnIndexVal) {\n    (void)intr; /* Unused in mock */\n    (void)srnIndex; /* Unused in mock */\n    (void)srnIndexVal; /* Unused in mock */\n}\n\nvoid IfxSrc_initOtgb(volatile Ifx_INT *intr, IfxSrc_OtgbConfig *OtgbConfig) {\n    (void)intr; /* Unused in mock */\n    (void)OtgbConfig; /* Unused in mock */\n}\n\nvoid IfxSrc_initOtgbConfig(IfxSrc_OtgbConfig *OtgbConfig) {\n    (void)OtgbConfig; /* Unused in mock */\n}\n\nvoid IfxSrc_configOtgbServiceProviderTrigger(volatile Ifx_INT *intr, IfxSrc_spConfig *spConfig) {\n    (void)intr; /* Unused in mock */\n    (void)spConfig; /* Unused in mock */\n}\n\nvoid IfxSrc_configureAccessToSrcs(IfxApApu_ApuConfig *apConfig) {\n    (void)apConfig; /* Unused in mock */\n}\n",
    "ifxegtm_pinmap.h": "#ifndef IFXEGTM_PINMAP_H\n#define IFXEGTM_PINMAP_H\n\n#include \"illd_types/Ifx_Types.h\"\n\n#include \"IfxEgtm_Atom.h\"\n/*\n * Minimal stub mock for IfxEgtm_PinMap.h\n * Auto-generated because production code includes this header\n * but no zHeaders information was found.\n * \n * Add function declarations here as needed.\n */\n\n\n/* EGTM Pin mapping variables - auto-injected from production code */\nextern const IfxEgtm_Atom_ToutMap IfxEgtm_ATOM0_0N_TOUT65_P20_9_OUT;\nextern const IfxEgtm_Atom_ToutMap IfxEgtm_ATOM0_0_TOUT64_P20_8_OUT;\nextern const IfxEgtm_Atom_ToutMap IfxEgtm_ATOM0_1N_TOUT67_P20_11_OUT;\nextern const IfxEgtm_Atom_ToutMap IfxEgtm_ATOM0_1_TOUT66_P20_10_OUT;\nextern const IfxEgtm_Atom_ToutMap IfxEgtm_ATOM0_2N_TOUT69_P20_13_OUT;\nextern const IfxEgtm_Atom_ToutMap IfxEgtm_ATOM0_2_TOUT68_P20_12_OUT;\n#endif /* IFXEGTM_PINMAP_H */\n",
    "ifxegtm_pinmap.c": "\n/*\n * Minimal stub implementation for IfxEgtm_PinMap.h\n * Add function implementations here as needed.\n */\n\n/* EGTM Pin variable definitions - auto-injected, safe {0} initializers */\nconst IfxEgtm_Atom_ToutMap IfxEgtm_ATOM0_0N_TOUT65_P20_9_OUT = {0};\nconst IfxEgtm_Atom_ToutMap IfxEgtm_ATOM0_0_TOUT64_P20_8_OUT = {0};\nconst IfxEgtm_Atom_ToutMap IfxEgtm_ATOM0_1N_TOUT67_P20_11_OUT = {0};\nconst IfxEgtm_Atom_ToutMap IfxEgtm_ATOM0_1_TOUT66_P20_10_OUT = {0};\nconst IfxEgtm_Atom_ToutMap IfxEgtm_ATOM0_2N_TOUT69_P20_13_OUT = {0};\nconst IfxEgtm_Atom_ToutMap IfxEgtm_ATOM0_2_TOUT68_P20_12_OUT = {0};\n",
    "IfxStm.h": "#ifndef IFXSTM_H\n#define IFXSTM_H\n\n#include \"illd_types/Ifx_Types.h\"  /* Provides Ifx_STM, uint32, Ifx_TickTime, etc. */\n\n/* NOTE: Ifx_STM is already defined in illd_types/Ifx_Types.h - do NOT redefine */\n/* Global STM instances - defined in ifx_types.c */\nextern Ifx_STM MODULE_STM0;\n/* Timer functions - 2026-02-20 Yvan: Added IfxStm_get and IfxStm_getFrequency */\n\n/* ============= Function Declarations ============= */\nuint64 IfxStm_get(Ifx_STM *stm);\nfloat32 IfxStm_getFrequency(Ifx_STM *stm);\nsint32 IfxStm_getTicksFromMilliseconds(Ifx_STM *stm, uint32 milliSeconds);\nsint32 IfxStm_getTicksFromMicroseconds(Ifx_STM *stm, uint32 microSeconds);\n\n#endif /* IFXSTM_H */",
    "IfxStm.c": "\n/* MODULE_STM0 is defined in ifx_types.c — only use extern from IfxStm.h */\n\n/* 2026-02-20 Yvan: Added IfxStm_get and IfxStm_getFrequency mocks */\nuint64 IfxStm_get(Ifx_STM *stm) {\n    (void)stm;  /* Unused in mock */\n    return 0ULL;  /* Return 0 for mock timer value */\n}\n\nfloat32 IfxStm_getFrequency(Ifx_STM *stm) {\n    (void)stm;  /* Unused in mock */\n    return 100000000.0f;  /* Return 100MHz as mock frequency */\n}\n\nsint32 IfxStm_getTicksFromMilliseconds(Ifx_STM *stm, uint32 millis) {\n    (void)stm;  /* Unused in mock */\n    return (sint32)(millis * 1000);  /* Simple conversion for testing */\n}\n\nsint32 IfxStm_getTicksFromMicroseconds(Ifx_STM *stm, uint32 micros) {\n    (void)stm;  /* Unused in mock */\n    return (sint32)micros;\n}\n",
    "ifxegtm_atom.h": "#ifndef IFXEGTM_ATOM_H\n#define IFXEGTM_ATOM_H\n\n#include \"illd_types/Ifx_Types.h\"\n\n/*\n * Auto-generated stub for IfxEgtm_Atom.h\n * This header was included by other mock headers but didn't exist.\n * Add type/function definitions here as needed.\n */\n\n/* GTM ATOM (ARU-connected Timer Output Module) types */\n/* IfxGtm_Atom_Ch - from illd_types/Ifx_Types.h */\n/* IfxGtm_Atom_ToutMap - from illd_types/Ifx_Types.h */\n\n#endif /* IFXEGTM_ATOM_H */\n",
    "ifxegtm_atom.c": "\n/* Auto-generated stub implementation for IfxEgtm_Atom.h */\n",
    "ifxport.h": "/* Auto-generated mock header from real iLLD: IfxPort.h */\n#ifndef IFXPORT_H\n#define IFXPORT_H\n\n#include \"Ifx_Types.h\"\n\n/* Function declarations (extracted from real iLLD) */\nvoid IfxPort_togglePin(Ifx_P *port, uint8 pinIndex);\n\n#endif /* IFXPORT_H */\n",
    "ifxport.c": "/* Auto-generated mock implementations for: IfxPort.h */\n\nstatic uint32 s_togglePin_count = 0;\n\nvoid IfxPort_togglePin(Ifx_P *port, uint8 pinIndex) {\n    (void)port;\n    (void)pinIndex;\n    s_togglePin_count++;\n}\n\nuint32 IfxPort_Mock_GetCallCount_togglePin(void) {\n    return s_togglePin_count;\n}\n"
  },
  "test_file_contents": {
    "test_EGTM_ATOM_3_Phase_Inverter_PWM.c": "#include \"unity.h\"\n#include \"Ifx_Types.h\"\n#include \"egtm_atom_3_phase_inverter_pwm.h\"\n\n// TC4xx target iLLD mock headers\n#include \"IfxEgtm.h\"\n#include \"IfxEgtm_Cmu.h\"\n#include \"IfxEgtm_Dtm.h\"\n#include \"IfxEgtm_Pwm.h\"\n#include \"IfxPort.h\"\n\nvoid setUp(void)\n{\n    // Reset all driver mocks before each test\n    IfxEgtm_Mock_Reset();\n    IfxEgtm_Cmu_Mock_Reset();\n    IfxEgtm_Dtm_Mock_Reset();\n    IfxEgtm_Pwm_Mock_Reset();\n    IfxPort_Mock_Reset();\n}\n\nvoid tearDown(void) {}\n\n// 1) Verify init calls the expected TC4xx driver APIs (migration guard)\nvoid test_initEgtmAtom3phInv_CallsExpectedDriverAPIs(void)\n{\n    // Act\n    initEgtmAtom3phInv();\n\n    // Assert: TC4xx eGTM enable + CMU clocks + DTM clock source configured\n    TEST_ASSERT_TRUE(IfxEgtm_Mock_GetCallCount_enable() > 0);\n    TEST_ASSERT_TRUE(IfxEgtm_Cmu_Mock_GetCallCount_enableClocks() > 0);\n    TEST_ASSERT_TRUE(IfxEgtm_Dtm_Mock_GetCallCount_setClockSource() > 0);\n\n    // Assert: Unified PWM driver config/init/start (sync-start enabled)\n    TEST_ASSERT_TRUE(IfxEgtm_Pwm_Mock_GetCallCount_initConfig() > 0);\n    TEST_ASSERT_TRUE(IfxEgtm_Pwm_Mock_GetCallCount_init() > 0);\n    TEST_ASSERT_TRUE(IfxEgtm_Pwm_Mock_GetCallCount_startSyncedChannels() > 0);\n\n    // Assert: LED GPIO configured and driven to known state\n    TEST_ASSERT_TRUE(IfxPort_Mock_GetCallCount_setPinModeOutput() > 0);\n    TEST_ASSERT_TRUE(IfxPort_Mock_GetCallCount_setPinState() > 0);\n}\n\n// 2) Validate key configuration values observable via mocks after init\n//    - CMU clock mask (non-zero: FXCLK_0 + CLK0 required)\n//    - DTM clock source configured (non-zero)\n//    - No duty update issued during init (syncStart only; syncUpdate occurs on runtime)\nvoid test_initEgtmAtom3phInv_SetsExpectedConfigValues(void)\n{\n    // Act\n    initEgtmAtom3phInv();\n\n    // Value checks via available capture helpers\n    uint32 clkMask = IfxEgtm_Cmu_Mock_GetLastArg_enableClocks_clkMask();\n    TEST_ASSERT_TRUE(clkMask != 0u);\n\n    uint32 dtmClkSrc = IfxEgtm_Dtm_Mock_GetLastArg_setClockSource();\n    TEST_ASSERT_TRUE(dtmClkSrc != 0u);\n\n    // Sync-start must be performed at init as per PWM_SYNCSTART = True\n    TEST_ASSERT_TRUE(IfxEgtm_Pwm_Mock_GetCallCount_startSyncedChannels() > 0);\n\n    // No duty array pushed during init (syncUpdate occurs on runtime updates)\n    TEST_ASSERT_EQUAL_UINT32(0u, IfxEgtm_Pwm_Mock_GetArgHistoryCount_updateDuty());\n}\n\n// 3) Single-call runtime update: duties are applied immediately and match driver state\nvoid test_updateEgtmAtom3phInvDuty_SingleCall_UpdatesValues(void)\n{\n    // Arrange\n    initEgtmAtom3phInv();\n\n    // Act\n    updateEgtmAtom3phInvDuty();\n\n    // Assert: TC4xx unified driver immediate update API called\n    TEST_ASSERT_TRUE(IfxEgtm_Pwm_Mock_GetCallCount_updateChannelsDutyImmediate() > 0);\n\n    // Assert: Values passed to driver match production's duty array (coherent multi-channel update)\n    float32 chU = IfxEgtm_Pwm_Mock_GetLastArrayArg_updateDuty(0);\n    float32 chV = IfxEgtm_Pwm_Mock_GetLastArrayArg_updateDuty(1);\n    float32 chW = IfxEgtm_Pwm_Mock_GetLastArrayArg_updateDuty(2);\n\n    TEST_ASSERT_FLOAT_WITHIN(0.001f, g_egtmAtom3phInv.dutyCycles[0], chU);\n    TEST_ASSERT_FLOAT_WITHIN(0.001f, g_egtmAtom3phInv.dutyCycles[1], chV);\n    TEST_ASSERT_FLOAT_WITHIN(0.001f, g_egtmAtom3phInv.dutyCycles[2], chW);\n}\n\n// 4) Multiple updates: verify equal step progression across all three channels (independent updates, syncUpdate)\nvoid test_updateEgtmAtom3phInvDuty_MultipleCalls_ProgressesCorrectly(void)\n{\n    // Arrange\n    initEgtmAtom3phInv();\n\n    // Act: two updates → two immediate multi-channel updates captured by the mock\n    updateEgtmAtom3phInvDuty();\n    updateEgtmAtom3phInvDuty();\n\n    // Assert: at least two captured arrays\n    uint32 histCount = IfxEgtm_Pwm_Mock_GetArgHistoryCount_updateDuty();\n    TEST_ASSERT_TRUE(histCount >= 2u);\n\n    // Compare per-channel deltas between consecutive updates\n    float32 u1 = IfxEgtm_Pwm_Mock_GetArgHistory_updateDuty(0u, 0u);\n    float32 u2 = IfxEgtm_Pwm_Mock_GetArgHistory_updateDuty(1u, 0u);\n    float32 v1 = IfxEgtm_Pwm_Mock_GetArgHistory_updateDuty(0u, 1u);\n    float32 v2 = IfxEgtm_Pwm_Mock_GetArgHistory_updateDuty(1u, 1u);\n    float32 w1 = IfxEgtm_Pwm_Mock_GetArgHistory_updateDuty(0u, 2u);\n    float32 w2 = IfxEgtm_Pwm_Mock_GetArgHistory_updateDuty(1u, 2u);\n\n    float32 du = u2 - u1;\n    float32 dv = v2 - v1;\n    float32 dw = w2 - w1;\n\n    // All channels advance by the same step, positive direction\n    TEST_ASSERT_TRUE(du > 0.0f);\n    TEST_ASSERT_FLOAT_WITHIN(0.001f, du, dv);\n    TEST_ASSERT_FLOAT_WITHIN(0.001f, du, dw);\n}\n\n// 5) Boundary/Wrap-around: values ramp and then wrap to low range (near zero) coherently\nvoid test_updateEgtmAtom3phInvDuty_BoundaryWrapAround(void)\n{\n    // Arrange\n    initEgtmAtom3phInv();\n\n    // Establish a positive step from first two calls\n    updateEgtmAtom3phInvDuty();\n    updateEgtmAtom3phInvDuty();\n\n    uint32 hc = IfxEgtm_Pwm_Mock_GetArgHistoryCount_updateDuty();\n    TEST_ASSERT_TRUE(hc >= 2u);\n\n    float32 prevPrevU = IfxEgtm_Pwm_Mock_GetArgHistory_updateDuty(hc - 2u, 0u);\n    float32 prevU     = IfxEgtm_Pwm_Mock_GetArgHistory_updateDuty(hc - 1u, 0u);\n    float32 step      = prevU - prevPrevU;\n    TEST_ASSERT_TRUE(step > 0.0f);\n\n    bool wrappedU = false, wrappedV = false, wrappedW = false;\n\n    // Iterate sufficiently to observe wrap-around (100% boundary not needed as a constant)\n    for (uint32 i = 0u; i < 300u && !(wrappedU && wrappedV && wrappedW); ++i)\n    {\n        float32 lastU = IfxEgtm_Pwm_Mock_GetLastArrayArg_updateDuty(0u);\n        float32 lastV = IfxEgtm_Pwm_Mock_GetLastArrayArg_updateDuty(1u);\n        float32 lastW = IfxEgtm_Pwm_Mock_GetLastArrayArg_updateDuty(2u);\n\n        updateEgtmAtom3phInvDuty();\n\n        float32 nowU = IfxEgtm_Pwm_Mock_GetLastArrayArg_updateDuty(0u);\n        float32 nowV = IfxEgtm_Pwm_Mock_GetLastArrayArg_updateDuty(1u);\n        float32 nowW = IfxEgtm_Pwm_Mock_GetLastArrayArg_updateDuty(2u);\n\n        if (!wrappedU && (nowU < lastU)) { wrappedU = true; TEST_ASSERT_TRUE(nowU <= (step + 1.0f)); }\n        if (!wrappedV && (nowV < lastV)) { wrappedV = true; TEST_ASSERT_TRUE(nowV <= (step + 1.0f)); }\n        if (!wrappedW && (nowW < lastW)) { wrappedW = true; TEST_ASSERT_TRUE(nowW <= (step + 1.0f)); }\n    }\n\n    TEST_ASSERT_TRUE(wrappedU);\n    TEST_ASSERT_TRUE(wrappedV);\n    TEST_ASSERT_TRUE(wrappedW);\n}\n\n// 6) No re-initialization during runtime updates; only the update API is invoked repeatedly\nvoid test_updateEgtmAtom3phInvDuty_DoesNotReInit(void)\n{\n    // Arrange\n    initEgtmAtom3phInv();\n\n    uint32 initInitCount   = IfxEgtm_Pwm_Mock_GetCallCount_init();\n    uint32 initEnableCount = IfxEgtm_Mock_GetCallCount_enable();\n    uint32 initClkCount    = IfxEgtm_Cmu_Mock_GetCallCount_enableClocks();\n    uint32 initDtmCount    = IfxEgtm_Dtm_Mock_GetCallCount_setClockSource();\n\n    // Act: perform multiple runtime updates\n    updateEgtmAtom3phInvDuty();\n    updateEgtmAtom3phInvDuty();\n    updateEgtmAtom3phInvDuty();\n\n    // Assert: no re-init or re-enable paths taken\n    TEST_ASSERT_EQUAL_UINT32(initInitCount,   IfxEgtm_Pwm_Mock_GetCallCount_init());\n    TEST_ASSERT_EQUAL_UINT32(initEnableCount, IfxEgtm_Mock_GetCallCount_enable());\n    TEST_ASSERT_EQUAL_UINT32(initClkCount,    IfxEgtm_Cmu_Mock_GetCallCount_enableClocks());\n    TEST_ASSERT_EQUAL_UINT32(initDtmCount,    IfxEgtm_Dtm_Mock_GetCallCount_setClockSource());\n\n    // Assert: runtime update API invoked on each call\n    TEST_ASSERT_EQUAL_UINT32(3u, IfxEgtm_Pwm_Mock_GetCallCount_updateChannelsDutyImmediate());\n    TEST_ASSERT_EQUAL_UINT32(3u, IfxEgtm_Pwm_Mock_GetArgHistoryCount_updateDuty());\n}\n"
  },
  "production_file_contents": {},
  "build_result": null,
  "test_result": null,
  "timestamp": "2026-03-24T05:46:08.062166"
}