{
  "meta": {
    "schema_version": "1.0",
    "last_updated_by": "hardware",
    "last_updated_at": "2026-03-31T08:43:46.191501",
    "build_sequence": [
      "requirements",
      "hardware"
    ],
    "corrections_log": []
  },
  "requirements": {
    "generation_mode": "MIGRATION",
    "migration_info": {
      "has_reference": true,
      "reference_family": "TC3xx",
      "target_family": "TC4xx",
      "migration_required": true,
      "driver_mappings": {
        "IfxScuWdt": "IfxWtu",
        "IfxGtm_Pwm": "IfxEgtm_Pwm"
      },
      "header_mappings": {
        "IfxScuWdt.h": "IfxWtu.h",
        "IfxGtm_Pwm.h": "IfxEgtm_Pwm.h",
        "IfxGtm_PinMap.h": "IfxEgtm_PinMap.h"
      },
      "api_changes": [
        {
          "from": "initGtmTom3phInv",
          "to": "initEgtmAtom3phInv",
          "reason": "TC3xx→TC4xx function name transform"
        },
        {
          "from": "updateGtmTom3phInvDuty",
          "to": "updateEgtmAtom3phInvDuty",
          "reason": "TC3xx→TC4xx function name transform"
        },
        {
          "from": "interruptGtmTom*",
          "to": "interruptEgtmAtom*",
          "reason": "TC3xx→TC4xx ISR naming"
        },
        {
          "from": "IfxScuWdt_disableCpuWatchdog",
          "to": "IfxWtu_disableCpuWatchdog",
          "reason": "TC3xx→TC4xx watchdog migration"
        },
        {
          "from": "IfxScuWdt_disableSafetyWatchdog",
          "to": "IfxWtu_disableSystemWatchdog",
          "reason": "TC3xx→TC4xx watchdog naming"
        },
        {
          "from": "IfxGtm_Pwm_initConfig",
          "to": "IfxEgtm_Pwm_initConfig",
          "reason": "GTM→EGTM driver migration"
        },
        {
          "from": "IfxGtm_Pwm_init",
          "to": "IfxEgtm_Pwm_init",
          "reason": "GTM→EGTM driver migration"
        },
        {
          "from": "IfxGtm_Pwm_updateChannelsDutyImmediate",
          "to": "IfxEgtm_Pwm_updateChannelsDutyImmediate",
          "reason": "GTM→EGTM driver migration"
        },
        {
          "from": "&MODULE_GTM",
          "to": "&MODULE_EGTM",
          "reason": "GTM→EGTM module base"
        }
      ],
      "function_names_to_preserve": [
        "initEgtmAtom3phInv",
        "updateEgtmAtom3phInvDuty",
        "EgtmAtomPeriodIsr"
      ]
    },
    "peripheral_requirement": {
      "type": "PWM",
      "driver_available": true,
      "driver_name": "IfxEgtm_Pwm",
      "purpose": "Three-phase complementary, center-aligned PWM at 20 kHz using EGTM Cluster 1 ATOM1 CH0/1/2 with DTM (1 us dead-time), syncStart+syncUpdate, and a period ISR toggling LED P03.9.",
      "driver_locked": true,
      "driver_selection_source": "engine_scored"
    },
    "signal_requirements": {
      "egtm_cluster": 1,
      "atom_module": 1,
      "primary_channels": [
        0,
        1,
        2
      ],
      "dtm_enabled": true,
      "complementary_inverted": true,
      "fxclk_source": "FXCLK0",
      "sync_start": true,
      "sync_update": true,
      "center_aligned": true,
      "outputs": [
        {
          "phase": "U",
          "high_side_pin": "P20.8",
          "high_side_tout": "TOUT64",
          "low_side_pin": "P20.9",
          "low_side_tout": "TOUT65",
          "primary_atom": "ATOM1_CH0"
        },
        {
          "phase": "V",
          "high_side_pin": "P20.10",
          "high_side_tout": "TOUT66",
          "low_side_pin": "P20.11",
          "low_side_tout": "TOUT67",
          "primary_atom": "ATOM1_CH1"
        },
        {
          "phase": "W",
          "high_side_pin": "P20.12",
          "high_side_tout": "TOUT68",
          "low_side_pin": "P20.13",
          "low_side_tout": "TOUT69",
          "primary_atom": "ATOM1_CH2"
        }
      ],
      "interrupt": {
        "type": "period",
        "cpu": "CPU0",
        "priority": 20,
        "isr_name": "EgtmAtomPeriodIsr"
      },
      "led": {
        "pin": "P03.9",
        "polarity": "low_active",
        "function": "toggle in period ISR"
      }
    },
    "timing_requirements": {
      "pwm_frequency_hz": 20000,
      "dead_time_ns": 1000,
      "duty_cycle_init_percent": {
        "U": 25,
        "V": 50,
        "W": 75
      },
      "duty_step_percent": 10
    },
    "device_configuration": {
      "target_device_macro": "DEVICE_TC4DX",
      "pin_package": "IFX_PIN_PACKAGE_BGA436_COM",
      "device_family": "TC4xx",
      "clock_requirements": {
        "requires_xtal": true,
        "expected_system_freq_mhz": 300
      }
    },
    "code_structure": {
      "file_pattern": "reference",
      "expected_files": [
        "EGTM_ATOM_3_Phase_Inverter_PWM.c",
        "EGTM_ATOM_3_Phase_Inverter_PWM.h"
      ],
      "has_cpu_files": true
    },
    "reference_context": {
      "includes_used": [
        "Ifx_Types.h",
        "IfxGtm_Pwm.h",
        "IfxPort.h",
        "IfxPort_Pinmap.h",
        "IfxCpu.h",
        "IfxScuWdt.h"
      ],
      "function_patterns": [
        "initGtmTom3phInv",
        "updateGtmTom3phInvDuty"
      ],
      "peripheral_usage": {
        "GTM": "3-phase PWM generation (reference used GTM TOM; target uses EGTM ATOM via IfxEgtm_Pwm)",
        "Port": "LED and pin configuration",
        "Cpu": "Interrupt setup and event control",
        "Watchdog": "Disable CPU and safety/system watchdogs at init"
      }
    },
    "migration_numerical_values": {
      "NUM_OF_CHANNELS": {
        "value": 3.0,
        "unit": "",
        "label": "Number of channels"
      },
      "PHASE_U_DUTY": {
        "value": 25.0,
        "unit": "%",
        "label": "Phase U initial duty cycle"
      },
      "PHASE_V_DUTY": {
        "value": 50.0,
        "unit": "%",
        "label": "Phase V initial duty cycle"
      },
      "PHASE_W_DUTY": {
        "value": 75.0,
        "unit": "%",
        "label": "Phase W initial duty cycle"
      },
      "PHASE_DUTY_STEP": {
        "value": 10.0,
        "unit": "%",
        "label": "Duty cycle step increment"
      },
      "PWM_FREQUENCY": {
        "value": 20000.0,
        "unit": "Hz",
        "label": "PWM switching frequency"
      },
      "ISR_PRIORITY_ATOM": {
        "value": 20.0,
        "unit": "",
        "label": "ISR priority"
      },
      ".rising": {
        "value": 1e-06,
        "unit": "",
        "label": ".rising"
      },
      ".falling": {
        "value": 1e-06,
        "unit": "",
        "label": ".falling"
      },
      ".phase": {
        "value": 0.0,
        "unit": "",
        "label": ".phase"
      },
      "WAIT_TIME": {
        "value": 500.0,
        "unit": "ms",
        "label": "Wait / delay time"
      }
    },
    "template_compatibility": {
      "validated": true,
      "supported_peripherals": [
        "PWM",
        "GTM",
        "EGTM",
        "GPIO",
        "INTERRUPT",
        "CPU"
      ],
      "suggested_drivers": {
        "PWM": [
          "IfxEgtm_Pwm",
          "IfxGtm_Atom_Pwm",
          "IfxEgtm_Tom_Pwm",
          "IfxGtm_Tom_Pwm",
          "IfxGtm_Pwm",
          "IfxEgtm_Atom_Pwm"
        ],
        "GTM": [
          "IfxGtm_PinMap",
          "IfxGtm_Tbu",
          "IfxGtm",
          "IfxGtm_Psm",
          "IfxGtm_Dtm",
          "IfxGtm_Spe",
          "IfxGtm_Pwm",
          "IfxGtm_Trigger",
          "IfxGtm_Input"
        ],
        "EGTM": [
          "IfxEgtm_PinMap",
          "IfxEgtm_cfg_TC4Dx",
          "IfxEgtm_Input",
          "IfxEgtm_Pwm",
          "IfxEgtm",
          "IfxEgtm_Atom",
          "IfxEgtm_Cmu",
          "IfxEgtm_Dtm",
          "IfxEgtm_Spe",
          "IfxEgtm_Tbu",
          "IfxEgtm_Tim",
          "IfxEgtm_Tom",
          "IfxEgtm_Trigger",
          "IfxEgtm_Tom_Pwm",
          "IfxEgtm_Tom_Timer",
          "IfxEgtm_Tim_In",
          "IfxEgtm_Tim_Timer",
          "IfxEgtm_Atom_Pwm",
          "IfxEgtm_Atom_Timer"
        ],
        "GPIO": [
          "IfxPort",
          "IfxPort_PinMap",
          "IfxScrPort",
          "IfxPort_Io",
          "IfxPort_cfg_TC4Dx"
        ],
        "INTERRUPT": [
          "IfxCpu_Irq",
          "IfxScrCpuIrq"
        ],
        "CPU": [
          "IfxCpu"
        ]
      },
      "warnings": []
    },
    "header_documentation_available": true,
    "config_values_extracted": 54
  },
  "hardware": {
    "microcontroller": {
      "model": "TC49xD7",
      "verified": true
    },
    "peripheral_instance": {
      "module": "EGTM.CLS1.ATOM1",
      "channels": [
        0,
        1,
        2
      ]
    },
    "pin_assignments": [
      {
        "signal": "PHASE_U_HS",
        "port_pin": "P20.8",
        "function": "TOUT64",
        "pin_macro": "IfxEgtm_ATOM1_0N_TOUT64_P20_8_OUT",
        "is_complementary": false,
        "verified": true,
        "source": "hardware_verified",
        "_original_pin_macro": "IfxEgtm_ATOM1_0_TOUT64_P20_8_OUT"
      },
      {
        "signal": "PHASE_U_LS",
        "port_pin": "P20.9",
        "function": "TOUT65",
        "pin_macro": "IfxEgtm_ATOM1_0_TOUT65_P20_9_OUT",
        "is_complementary": true,
        "verified": true,
        "source": "hardware_verified",
        "_original_pin_macro": "IfxEgtm_ATOM1_0N_TOUT65_P20_9_OUT"
      },
      {
        "signal": "PHASE_V_HS",
        "port_pin": "P20.10",
        "function": "TOUT66",
        "pin_macro": "IfxEgtm_ATOM1_1N_TOUT66_P20_10_OUT",
        "is_complementary": false,
        "verified": true,
        "source": "hardware_verified",
        "_original_pin_macro": "IfxEgtm_ATOM1_1_TOUT66_P20_10_OUT"
      },
      {
        "signal": "PHASE_V_LS",
        "port_pin": "P20.11",
        "function": "TOUT67",
        "pin_macro": "IfxEgtm_ATOM1_1_TOUT67_P20_11_OUT",
        "is_complementary": true,
        "verified": true,
        "source": "hardware_verified",
        "_original_pin_macro": "IfxEgtm_ATOM1_1N_TOUT67_P20_11_OUT"
      },
      {
        "signal": "PHASE_W_HS",
        "port_pin": "P20.12",
        "function": "TOUT68",
        "pin_macro": "IfxEgtm_ATOM1_0_TOUT68_P20_12_OUT",
        "is_complementary": false,
        "verified": true,
        "source": "hardware_verified",
        "_original_pin_macro": "IfxEgtm_ATOM1_2_TOUT68_P20_12_OUT"
      },
      {
        "signal": "PHASE_W_LS",
        "port_pin": "P20.13",
        "function": "TOUT69",
        "pin_macro": "IfxEgtm_ATOM1_1_TOUT69_P20_13_OUT",
        "is_complementary": true,
        "verified": true,
        "source": "hardware_verified",
        "_original_pin_macro": "IfxEgtm_ATOM1_2N_TOUT69_P20_13_OUT"
      }
    ],
    "clock_configuration": {
      "xtal_frequency_mhz": 25,
      "system_frequency_mhz": 500
    },
    "validation": {
      "all_verified": true,
      "conflicts": [],
      "reference_pins_valid": false
    },
    "template_validation": {
      "supported_peripherals": [
        "PWM",
        "GTM",
        "EGTM",
        "GPIO",
        "INTERRUPT",
        "CPU"
      ],
      "suggested_drivers": {
        "PWM": [
          "IfxEgtm_Pwm",
          "IfxGtm_Atom_Pwm",
          "IfxEgtm_Tom_Pwm",
          "IfxGtm_Tom_Pwm",
          "IfxGtm_Pwm",
          "IfxEgtm_Atom_Pwm"
        ],
        "GTM": [
          "IfxGtm_PinMap",
          "IfxGtm_Tbu",
          "IfxGtm",
          "IfxGtm_Psm",
          "IfxGtm_Dtm",
          "IfxGtm_Spe",
          "IfxGtm_Pwm",
          "IfxGtm_Trigger",
          "IfxGtm_Input"
        ],
        "EGTM": [
          "IfxEgtm_PinMap",
          "IfxEgtm_cfg_TC4Dx",
          "IfxEgtm_Input",
          "IfxEgtm_Pwm",
          "IfxEgtm",
          "IfxEgtm_Atom",
          "IfxEgtm_Cmu",
          "IfxEgtm_Dtm",
          "IfxEgtm_Spe",
          "IfxEgtm_Tbu",
          "IfxEgtm_Tim",
          "IfxEgtm_Tom",
          "IfxEgtm_Trigger",
          "IfxEgtm_Tom_Pwm",
          "IfxEgtm_Tom_Timer",
          "IfxEgtm_Tim_In",
          "IfxEgtm_Tim_Timer",
          "IfxEgtm_Atom_Pwm",
          "IfxEgtm_Atom_Timer"
        ],
        "GPIO": [
          "IfxPort",
          "IfxPort_PinMap",
          "IfxScrPort",
          "IfxPort_Io",
          "IfxPort_cfg_TC4Dx"
        ],
        "INTERRUPT": [
          "IfxCpu_Irq",
          "IfxScrCpuIrq"
        ],
        "CPU": [
          "IfxCpu"
        ]
      },
      "warnings": []
    }
  }
}