{
  "success": false,
  "errors": [
    {
      "file": "C:\\Users\\extpedj\\AppData\\Local\\Temp\\tdd_build_i6ir7zeo\\include/IfxGtm_Pwm.h",
      "line": 56,
      "category": "error",
      "message": "unknown type name 'IfxGtm_IrqMode'"
    },
    {
      "file": "C:\\Users\\extpedj\\AppData\\Local\\Temp\\tdd_build_i6ir7zeo\\src\\gtm_tom_3_phase_inverter_pwm.c",
      "line": 82,
      "category": "error",
      "message": "duplicate 'static'"
    },
    {
      "file": "C:\\Users\\extpedj\\AppData\\Local\\Temp\\tdd_build_i6ir7zeo\\src\\gtm_tom_3_phase_inverter_pwm.c",
      "line": 116,
      "category": "error",
      "message": "implicit declaration of function 'IfxGtm_enable' [-Wimplicit-function-declaration]"
    },
    {
      "file": "C:\\Users\\extpedj\\AppData\\Local\\Temp\\tdd_build_i6ir7zeo\\src\\gtm_tom_3_phase_inverter_pwm.c",
      "line": 119,
      "category": "error",
      "message": "implicit declaration of function 'IfxGtm_Cmu_getModuleFrequency'; did you mean 'IfxGtm_Cmu_setGclkFrequency'? [-Wimplicit-function-declaration]"
    },
    {
      "file": "C:\\Users\\extpedj\\AppData\\Local\\Temp\\tdd_build_i6ir7zeo\\src\\gtm_tom_3_phase_inverter_pwm.c",
      "line": 122,
      "category": "error",
      "message": "'IFXGTM_CMU_CLKEN_ALL' undeclared (first use in this function)"
    },
    {
      "file": "C:\\Users\\extpedj\\AppData\\Local\\Temp\\tdd_build_i6ir7zeo\\src\\gtm_tom_3_phase_inverter_pwm.c",
      "line": 131,
      "category": "error",
      "message": "'IfxGtm_Tom_Timer_Config' has no member named 'tom'"
    },
    {
      "file": "C:\\Users\\extpedj\\AppData\\Local\\Temp\\tdd_build_i6ir7zeo\\src\\gtm_tom_3_phase_inverter_pwm.c",
      "line": 33,
      "category": "error",
      "message": "'IfxGtm_Tom_1' undeclared (first use in this function); did you mean 'IfxGtm_Tom_Ch'?"
    },
    {
      "file": "C:\\Users\\extpedj\\AppData\\Local\\Temp\\tdd_build_i6ir7zeo\\src\\gtm_tom_3_phase_inverter_pwm.c",
      "line": 132,
      "category": "error",
      "message": "'IfxGtm_Tom_Timer_Config' has no member named 'timerChannel'"
    },
    {
      "file": "C:\\Users\\extpedj\\AppData\\Local\\Temp\\tdd_build_i6ir7zeo\\src\\gtm_tom_3_phase_inverter_pwm.c",
      "line": 133,
      "category": "error",
      "message": "'IfxGtm_Tom_Timer_Config' has no member named 'clock'"
    },
    {
      "file": "C:\\Users\\extpedj\\AppData\\Local\\Temp\\tdd_build_i6ir7zeo\\src\\gtm_tom_3_phase_inverter_pwm.c",
      "line": 35,
      "category": "error",
      "message": "'IfxGtm_Tom_Ch_ClkSrc_cmuFxclk0' undeclared (first use in this function)"
    },
    {
      "file": "C:\\Users\\extpedj\\AppData\\Local\\Temp\\tdd_build_i6ir7zeo\\src\\gtm_tom_3_phase_inverter_pwm.c",
      "line": 134,
      "category": "error",
      "message": "'IfxGtm_Tom_Timer_Config' has no member named 'triggerOut'"
    },
    {
      "file": "C:\\Users\\extpedj\\AppData\\Local\\Temp\\tdd_build_i6ir7zeo\\src\\gtm_tom_3_phase_inverter_pwm.c",
      "line": 148,
      "category": "error",
      "message": "implicit declaration of function 'IfxGtm_Cmu_getFxClkFrequency'; did you mean 'IfxGtm_Cmu_setGclkFrequency'? [-Wimplicit-function-declaration]"
    },
    {
      "file": "C:\\Users\\extpedj\\AppData\\Local\\Temp\\tdd_build_i6ir7zeo\\src\\gtm_tom_3_phase_inverter_pwm.c",
      "line": 43,
      "category": "error",
      "message": "'IfxGtm_TOM1_2_TOUT12_P00_3_OUT' undeclared (first use in this function)"
    },
    {
      "file": "C:\\Users\\extpedj\\AppData\\Local\\Temp\\tdd_build_i6ir7zeo\\src\\gtm_tom_3_phase_inverter_pwm.c",
      "line": 44,
      "category": "error",
      "message": "'IfxGtm_TOM1_4_TOUT14_P00_5_OUT' undeclared (first use in this function)"
    },
    {
      "file": "C:\\Users\\extpedj\\AppData\\Local\\Temp\\tdd_build_i6ir7zeo\\src\\gtm_tom_3_phase_inverter_pwm.c",
      "line": 45,
      "category": "error",
      "message": "'IfxGtm_TOM1_6_TOUT16_P00_7_OUT' undeclared (first use in this function)"
    },
    {
      "file": "C:\\Users\\extpedj\\AppData\\Local\\Temp\\tdd_build_i6ir7zeo\\src\\gtm_tom_3_phase_inverter_pwm.c",
      "line": 216,
      "category": "error",
      "message": "'IfxGtm_Pwm_Config' has no member named 'subModule'"
    },
    {
      "file": "C:\\Users\\extpedj\\AppData\\Local\\Temp\\tdd_build_i6ir7zeo\\src\\gtm_tom_3_phase_inverter_pwm.c",
      "line": 218,
      "category": "error",
      "message": "'IfxGtm_Pwm_Config' has no member named 'syncStart'"
    },
    {
      "file": "C:\\Users\\extpedj\\AppData\\Local\\Temp\\tdd_build_i6ir7zeo\\src\\gtm_tom_3_phase_inverter_pwm.c",
      "line": 220,
      "category": "error",
      "message": "'IfxGtm_Pwm_Config' has no member named 'channels'; did you mean 'numChannels'?"
    },
    {
      "file": "C:\\Users\\extpedj\\AppData\\Local\\Temp\\tdd_build_i6ir7zeo\\src\\gtm_tom_3_phase_inverter_pwm.c",
      "line": 222,
      "category": "error",
      "message": "'IfxGtm_Pwm_Config' has no member named 'dtmClockSource'"
    },
    {
      "file": "C:\\Users\\extpedj\\AppData\\Local\\Temp\\tdd_build_i6ir7zeo\\src\\gtm_tom_3_phase_inverter_pwm.c",
      "line": 222,
      "category": "error",
      "message": "'IfxGtm_Dtm_ClockSource_cmuClock0' undeclared (first use in this function)"
    },
    {
      "file": "C:\\Users\\extpedj\\AppData\\Local\\Temp\\tdd_build_i6ir7zeo\\src\\gtm_tom_3_phase_inverter_pwm.c",
      "line": 223,
      "category": "error",
      "message": "'IfxGtm_Pwm_Config' has no member named 'syncUpdateEnabled'"
    },
    {
      "file": "C:\\Users\\extpedj\\AppData\\Local\\Temp\\tdd_build_i6ir7zeo\\include/IfxGtm_Cmu.h",
      "line": 9,
      "category": "error",
      "message": "redeclaration of enumerator 'IfxGtm_Cmu_Clk_0'"
    },
    {
      "file": "C:\\Users\\extpedj\\AppData\\Local\\Temp\\tdd_build_i6ir7zeo\\include/IfxGtm_Cmu.h",
      "line": 10,
      "category": "error",
      "message": "redeclaration of enumerator 'IfxGtm_Cmu_Clk_1'"
    },
    {
      "file": "C:\\Users\\extpedj\\AppData\\Local\\Temp\\tdd_build_i6ir7zeo\\include/IfxGtm_Cmu.h",
      "line": 11,
      "category": "error",
      "message": "redeclaration of enumerator 'IfxGtm_Cmu_Clk_2'"
    },
    {
      "file": "C:\\Users\\extpedj\\AppData\\Local\\Temp\\tdd_build_i6ir7zeo\\include/IfxGtm_Cmu.h",
      "line": 12,
      "category": "error",
      "message": "redeclaration of enumerator 'IfxGtm_Cmu_Clk_3'"
    },
    {
      "file": "C:\\Users\\extpedj\\AppData\\Local\\Temp\\tdd_build_i6ir7zeo\\include/IfxGtm_Cmu.h",
      "line": 13,
      "category": "error",
      "message": "redeclaration of enumerator 'IfxGtm_Cmu_Clk_4'"
    },
    {
      "file": "C:\\Users\\extpedj\\AppData\\Local\\Temp\\tdd_build_i6ir7zeo\\include/IfxGtm_Cmu.h",
      "line": 14,
      "category": "error",
      "message": "redeclaration of enumerator 'IfxGtm_Cmu_Clk_5'"
    },
    {
      "file": "C:\\Users\\extpedj\\AppData\\Local\\Temp\\tdd_build_i6ir7zeo\\include/IfxGtm_Cmu.h",
      "line": 15,
      "category": "error",
      "message": "redeclaration of enumerator 'IfxGtm_Cmu_Clk_6'"
    },
    {
      "file": "C:\\Users\\extpedj\\AppData\\Local\\Temp\\tdd_build_i6ir7zeo\\include/IfxGtm_Cmu.h",
      "line": 16,
      "category": "error",
      "message": "redeclaration of enumerator 'IfxGtm_Cmu_Clk_7'"
    },
    {
      "file": "C:\\Users\\extpedj\\AppData\\Local\\Temp\\tdd_build_i6ir7zeo\\include/IfxGtm_Cmu.h",
      "line": 17,
      "category": "error",
      "message": "conflicting types for 'IfxGtm_Cmu_Clk'; have 'enum <anonymous>'"
    },
    {
      "file": "C:\\Users\\extpedj\\AppData\\Local\\Temp\\tdd_build_i6ir7zeo\\include/IfxGtm_Cmu.h",
      "line": 26,
      "category": "error",
      "message": "redeclaration of enumerator 'IfxGtm_Cmu_Fxclk_0'"
    },
    {
      "file": "C:\\Users\\extpedj\\AppData\\Local\\Temp\\tdd_build_i6ir7zeo\\include/IfxGtm_Cmu.h",
      "line": 27,
      "category": "error",
      "message": "redeclaration of enumerator 'IfxGtm_Cmu_Fxclk_1'"
    },
    {
      "file": "C:\\Users\\extpedj\\AppData\\Local\\Temp\\tdd_build_i6ir7zeo\\include/IfxGtm_Cmu.h",
      "line": 28,
      "category": "error",
      "message": "redeclaration of enumerator 'IfxGtm_Cmu_Fxclk_2'"
    },
    {
      "file": "C:\\Users\\extpedj\\AppData\\Local\\Temp\\tdd_build_i6ir7zeo\\include/IfxGtm_Cmu.h",
      "line": 29,
      "category": "error",
      "message": "redeclaration of enumerator 'IfxGtm_Cmu_Fxclk_3'"
    },
    {
      "file": "C:\\Users\\extpedj\\AppData\\Local\\Temp\\tdd_build_i6ir7zeo\\include/IfxGtm_Cmu.h",
      "line": 30,
      "category": "error",
      "message": "redeclaration of enumerator 'IfxGtm_Cmu_Fxclk_4'"
    },
    {
      "file": "C:\\Users\\extpedj\\AppData\\Local\\Temp\\tdd_build_i6ir7zeo\\include/IfxGtm_Cmu.h",
      "line": 31,
      "category": "error",
      "message": "conflicting types for 'IfxGtm_Cmu_Fxclk'; have 'enum <anonymous>'"
    },
    {
      "file": "C:\\Users\\extpedj\\AppData\\Local\\Temp\\tdd_build_i6ir7zeo\\test\\test_gtm_tom_3_phase_inverter_pwm.c",
      "line": 97,
      "category": "error",
      "message": "implicit declaration of function 'mock_IfxGtm_Pwm_updateChannelDeadTimeImmediate_getCallCount'; did you mean 'mock_IfxGtm_Pwm_updateChannelsDuty_getCallCount'? [-Wimplicit-function-declaration]"
    }
  ],
  "warnings": [],
  "stderr": "In file included from C:\\Users\\extpedj\\AppData\\Local\\Temp\\tdd_build_i6ir7zeo\\src\\gtm_tom_3_phase_inverter_pwm.c:19:\nC:\\Users\\extpedj\\AppData\\Local\\Temp\\tdd_build_i6ir7zeo\\include/IfxGtm_Pwm.h:56:5: error: unknown type name 'IfxGtm_IrqMode'\n   56 |     IfxGtm_IrqMode      mode;              /* IRQ mode */\n      |     ^~~~~~~~~~~~~~\nC:\\Users\\extpedj\\AppData\\Local\\Temp\\tdd_build_i6ir7zeo\\src\\gtm_tom_3_phase_inverter_pwm.c:82:1: error: duplicate 'static'\n   82 | static IFX_STATIC GtmTom3PhPwm_State g_gtnPwm = {0};\n      | ^~~~~~\nC:\\Users\\extpedj\\AppData\\Local\\Temp\\tdd_build_i6ir7zeo\\src\\gtm_tom_3_phase_inverter_pwm.c: In function 'initGtmTomPwm':\nC:\\Users\\extpedj\\AppData\\Local\\Temp\\tdd_build_i6ir7zeo\\src\\gtm_tom_3_phase_inverter_pwm.c:116:5: error: implicit declaration of function 'IfxGtm_enable' [-Wimplicit-function-declaration]\n  116 |     IfxGtm_enable(gtm);\n      |     ^~~~~~~~~~~~~\nC:\\Users\\extpedj\\AppData\\Local\\Temp\\tdd_build_i6ir7zeo\\src\\gtm_tom_3_phase_inverter_pwm.c:119:30: error: implicit declaration of function 'IfxGtm_Cmu_getModuleFrequency'; did you mean 'IfxGtm_Cmu_setGclkFrequency'? [-Wimplicit-function-declaration]\n  119 |         float32 moduleFreq = IfxGtm_Cmu_getModuleFrequency(gtm);\n      |                              ^~~~~~~~~~~~~~~~~~~~~~~~~~~~~\n      |                              IfxGtm_Cmu_setGclkFrequency\nC:\\Users\\extpedj\\AppData\\Local\\Temp\\tdd_build_i6ir7zeo\\src\\gtm_tom_3_phase_inverter_pwm.c:122:46: error: 'IFXGTM_CMU_CLKEN_ALL' undeclared (first use in this function)\n  122 |         IfxGtm_Cmu_enableClocks(gtm, (uint32)IFXGTM_CMU_CLKEN_ALL);\n      |                                              ^~~~~~~~~~~~~~~~~~~~\nC:\\Users\\extpedj\\AppData\\Local\\Temp\\tdd_build_i6ir7zeo\\src\\gtm_tom_3_phase_inverter_pwm.c:122:46: note: each undeclared identifier is reported only once for each function it appears in\nC:\\Users\\extpedj\\AppData\\Local\\Temp\\tdd_build_i6ir7zeo\\src\\gtm_tom_3_phase_inverter_pwm.c:131:13: error: 'IfxGtm_Tom_Timer_Config' has no member named 'tom'\n  131 |         tcfg.tom           = GTM_TOM_TIMEBASE_TOM;\n      |             ^\nC:\\Users\\extpedj\\AppData\\Local\\Temp\\tdd_build_i6ir7zeo\\src\\gtm_tom_3_phase_inverter_pwm.c:33:44: error: 'IfxGtm_Tom_1' undeclared (first use in this function); did you mean 'IfxGtm_Tom_Ch'?\n   33 | #define GTM_TOM_TIMEBASE_TOM               IfxGtm_Tom_1\n      |                                            ^~~~~~~~~~~~\nC:\\Users\\extpedj\\AppData\\Local\\Temp\\tdd_build_i6ir7zeo\\src\\gtm_tom_3_phase_inverter_pwm.c:131:30: note: in expansion of macro 'GTM_TOM_TIMEBASE_TOM'\n  131 |         tcfg.tom           = GTM_TOM_TIMEBASE_TOM;\n      |                              ^~~~~~~~~~~~~~~~~~~~\nC:\\Users\\extpedj\\AppData\\Local\\Temp\\tdd_build_i6ir7zeo\\src\\gtm_tom_3_phase_inverter_pwm.c:132:13: error: 'IfxGtm_Tom_Timer_Config' has no member named 'timerChannel'\n  132 |         tcfg.timerChannel  = GTM_TOM_TIMEBASE_CHANNEL;\n      |             ^\nC:\\Users\\extpedj\\AppData\\Local\\Temp\\tdd_build_i6ir7zeo\\src\\gtm_tom_3_phase_inverter_pwm.c:133:13: error: 'IfxGtm_Tom_Timer_Config' has no member named 'clock'\n  133 |         tcfg.clock         = GTM_TOM_TIMEBASE_CLOCK;     /* FXCLK0 */\n      |             ^\nC:\\Users\\extpedj\\AppData\\Local\\Temp\\tdd_build_i6ir7zeo\\src\\gtm_tom_3_phase_inverter_pwm.c:35:44: error: 'IfxGtm_Tom_Ch_ClkSrc_cmuFxclk0' undeclared (first use in this function)\n   35 | #define GTM_TOM_TIMEBASE_CLOCK             IfxGtm_Tom_Ch_ClkSrc_cmuFxclk0\n      |                                            ^~~~~~~~~~~~~~~~~~~~~~~~~~~~~~\nC:\\Users\\extpedj\\AppData\\Local\\Temp\\tdd_build_i6ir7zeo\\src\\gtm_tom_3_phase_inverter_pwm.c:133:30: note: in expansion of macro 'GTM_TOM_TIMEBASE_CLOCK'\n  133 |         tcfg.clock         = GTM_TOM_TIMEBASE_CLOCK;     /* FXCLK0 */\n      |                              ^~~~~~~~~~~~~~~~~~~~~~\nC:\\Users\\extpedj\\AppData\\Local\\Temp\\tdd_build_i6ir7zeo\\src\\gtm_tom_3_phase_inverter_pwm.c:134:13: error: 'IfxGtm_Tom_Timer_Config' has no member named 'triggerOut'\n  134 |         tcfg.triggerOut    = NULL_PTR;                   /* no external trigger */\n      |             ^\nC:\\Users\\extpedj\\AppData\\Local\\Temp\\tdd_build_i6ir7zeo\\src\\gtm_tom_3_phase_inverter_pwm.c:148:30: error: implicit declaration of function 'IfxGtm_Cmu_getFxClkFrequency'; did you mean 'IfxGtm_Cmu_setGclkFrequency'? [-Wimplicit-function-declaration]\n  148 |             float32 fxclk0 = IfxGtm_Cmu_getFxClkFrequency(gtm, IfxGtm_Cmu_Fxclk_0);\n      |                              ^~~~~~~~~~~~~~~~~~~~~~~~~~~~\n      |                              IfxGtm_Cmu_setGclkFrequency\nC:\\Users\\extpedj\\AppData\\Local\\Temp\\tdd_build_i6ir7zeo\\src\\gtm_tom_3_phase_inverter_pwm.c:43:45: error: 'IfxGtm_TOM1_2_TOUT12_P00_3_OUT' undeclared (first use in this function)\n   43 | #define PHASE_U_HS                         &IfxGtm_TOM1_2_TOUT12_P00_3_OUT\n      |                                             ^~~~~~~~~~~~~~~~~~~~~~~~~~~~~~\nC:\\Users\\extpedj\\AppData\\Local\\Temp\\tdd_build_i6ir7zeo\\src\\gtm_tom_3_phase_inverter_pwm.c:164:73: note: in expansion of macro 'PHASE_U_HS'\n  164 |         g_gtnPwm.outCfg[0].pin                   = (IfxGtm_Pwm_ToutMap*)PHASE_U_HS;\n      |                                                                         ^~~~~~~~~~\nC:\\Users\\extpedj\\AppData\\Local\\Temp\\tdd_build_i6ir7zeo\\src\\gtm_tom_3_phase_inverter_pwm.c:44:45: error: 'IfxGtm_TOM1_4_TOUT14_P00_5_OUT' undeclared (first use in this function)\n   44 | #define PHASE_V_HS                         &IfxGtm_TOM1_4_TOUT14_P00_5_OUT\n      |                                             ^~~~~~~~~~~~~~~~~~~~~~~~~~~~~~\nC:\\Users\\extpedj\\AppData\\Local\\Temp\\tdd_build_i6ir7zeo\\src\\gtm_tom_3_phase_inverter_pwm.c:171:73: note: in expansion of macro 'PHASE_V_HS'\n  171 |         g_gtnPwm.outCfg[1].pin                   = (IfxGtm_Pwm_ToutMap*)PHASE_V_HS;\n      |                                                                         ^~~~~~~~~~\nC:\\Users\\extpedj\\AppData\\Local\\Temp\\tdd_build_i6ir7zeo\\src\\gtm_tom_3_phase_inverter_pwm.c:45:45: error: 'IfxGtm_TOM1_6_TOUT16_P00_7_OUT' undeclared (first use in this function)\n   45 | #define PHASE_W_HS                         &IfxGtm_TOM1_6_TOUT16_P00_7_OUT\n      |                                             ^~~~~~~~~~~~~~~~~~~~~~~~~~~~~~\nC:\\Users\\extpedj\\AppData\\Local\\Temp\\tdd_build_i6ir7zeo\\src\\gtm_tom_3_phase_inverter_pwm.c:178:73: note: in expansion of macro 'PHASE_W_HS'\n  178 |         g_gtnPwm.outCfg[2].pin                   = (IfxGtm_Pwm_ToutMap*)PHASE_W_HS;\n      |                                                                         ^~~~~~~~~~\nC:\\Users\\extpedj\\AppData\\Local\\Temp\\tdd_build_i6ir7zeo\\src\\gtm_tom_3_phase_inverter_pwm.c:216:13: error: 'IfxGtm_Pwm_Config' has no member named 'subModule'\n  216 |         pcfg.subModule           = IfxGtm_Pwm_SubModule_tom;\n      |             ^\nC:\\Users\\extpedj\\AppData\\Local\\Temp\\tdd_build_i6ir7zeo\\src\\gtm_tom_3_phase_inverter_pwm.c:218:13: error: 'IfxGtm_Pwm_Config' has no member named 'syncStart'\n  218 |         pcfg.syncStart           = TRUE;\n      |             ^\nC:\\Users\\extpedj\\AppData\\Local\\Temp\\tdd_build_i6ir7zeo\\src\\gtm_tom_3_phase_inverter_pwm.c:220:14: error: 'IfxGtm_Pwm_Config' has no member named 'channels'; did you mean 'numChannels'?\n  220 |         pcfg.channels            = &g_gtnPwm.chCfg[0];\n      |              ^~~~~~~~\n      |              numChannels\nC:\\Users\\extpedj\\AppData\\Local\\Temp\\tdd_build_i6ir7zeo\\src\\gtm_tom_3_phase_inverter_pwm.c:222:13: error: 'IfxGtm_Pwm_Config' has no member named 'dtmClockSource'\n  222 |         pcfg.dtmClockSource      = IfxGtm_Dtm_ClockSource_cmuClock0;\n      |             ^\nC:\\Users\\extpedj\\AppData\\Local\\Temp\\tdd_build_i6ir7zeo\\src\\gtm_tom_3_phase_inverter_pwm.c:222:36: error: 'IfxGtm_Dtm_ClockSource_cmuClock0' undeclared (first use in this function)\n  222 |         pcfg.dtmClockSource      = IfxGtm_Dtm_ClockSource_cmuClock0;\n      |                                    ^~~~~~~~~~~~~~~~~~~~~~~~~~~~~~~~\nC:\\Users\\extpedj\\AppData\\Local\\Temp\\tdd_build_i6ir7zeo\\src\\gtm_tom_3_phase_inverter_pwm.c:223:13: error: 'IfxGtm_Pwm_Config' has no member named 'syncUpdateEnabled'\n  223 |         pcfg.syncUpdateEnabled   = TRUE;\n      |             ^\n\nIn file included from C:\\Users\\extpedj\\AppData\\Local\\Temp\\tdd_build_i6ir7zeo\\mocks\\mock_gtm_tom_3_phase_inverter_pwm.c:7:\nC:\\Users\\extpedj\\AppData\\Local\\Temp\\tdd_build_i6ir7zeo\\include/IfxGtm_Cmu.h:9:5: error: redeclaration of enumerator 'IfxGtm_Cmu_Clk_0'\n    9 |     IfxGtm_Cmu_Clk_0 = 0,\n      |     ^~~~~~~~~~~~~~~~\nIn file included from C:\\Users\\extpedj\\AppData\\Local\\Temp\\tdd_build_i6ir7zeo\\mocks\\mock_gtm_tom_3_phase_inverter_pwm.c:6:\nC:\\Users\\extpedj\\AppData\\Local\\Temp\\tdd_build_i6ir7zeo\\include/IfxGtm_Pwm.h:116:5: note: previous definition of 'IfxGtm_Cmu_Clk_0' with type 'enum <anonymous>'\n  116 |     IfxGtm_Cmu_Clk_0 = 0,\n      |     ^~~~~~~~~~~~~~~~\nC:\\Users\\extpedj\\AppData\\Local\\Temp\\tdd_build_i6ir7zeo\\include/IfxGtm_Cmu.h:10:5: error: redeclaration of enumerator 'IfxGtm_Cmu_Clk_1'\n   10 |     IfxGtm_Cmu_Clk_1,\n      |     ^~~~~~~~~~~~~~~~\nC:\\Users\\extpedj\\AppData\\Local\\Temp\\tdd_build_i6ir7zeo\\include/IfxGtm_Pwm.h:117:5: note: previous definition of 'IfxGtm_Cmu_Clk_1' with type 'enum <anonymous>'\n  117 |     IfxGtm_Cmu_Clk_1,\n      |     ^~~~~~~~~~~~~~~~\nC:\\Users\\extpedj\\AppData\\Local\\Temp\\tdd_build_i6ir7zeo\\include/IfxGtm_Cmu.h:11:5: error: redeclaration of enumerator 'IfxGtm_Cmu_Clk_2'\n   11 |     IfxGtm_Cmu_Clk_2,\n      |     ^~~~~~~~~~~~~~~~\nC:\\Users\\extpedj\\AppData\\Local\\Temp\\tdd_build_i6ir7zeo\\include/IfxGtm_Pwm.h:118:5: note: previous definition of 'IfxGtm_Cmu_Clk_2' with type 'enum <anonymous>'\n  118 |     IfxGtm_Cmu_Clk_2,\n      |     ^~~~~~~~~~~~~~~~\nC:\\Users\\extpedj\\AppData\\Local\\Temp\\tdd_build_i6ir7zeo\\include/IfxGtm_Cmu.h:12:5: error: redeclaration of enumerator 'IfxGtm_Cmu_Clk_3'\n   12 |     IfxGtm_Cmu_Clk_3,\n      |     ^~~~~~~~~~~~~~~~\nC:\\Users\\extpedj\\AppData\\Local\\Temp\\tdd_build_i6ir7zeo\\include/IfxGtm_Pwm.h:119:5: note: previous definition of 'IfxGtm_Cmu_Clk_3' with type 'enum <anonymous>'\n  119 |     IfxGtm_Cmu_Clk_3,\n      |     ^~~~~~~~~~~~~~~~\nC:\\Users\\extpedj\\AppData\\Local\\Temp\\tdd_build_i6ir7zeo\\include/IfxGtm_Cmu.h:13:5: error: redeclaration of enumerator 'IfxGtm_Cmu_Clk_4'\n   13 |     IfxGtm_Cmu_Clk_4,\n      |     ^~~~~~~~~~~~~~~~\nC:\\Users\\extpedj\\AppData\\Local\\Temp\\tdd_build_i6ir7zeo\\include/IfxGtm_Pwm.h:120:5: note: previous definition of 'IfxGtm_Cmu_Clk_4' with type 'enum <anonymous>'\n  120 |     IfxGtm_Cmu_Clk_4,\n      |     ^~~~~~~~~~~~~~~~\nC:\\Users\\extpedj\\AppData\\Local\\Temp\\tdd_build_i6ir7zeo\\include/IfxGtm_Cmu.h:14:5: error: redeclaration of enumerator 'IfxGtm_Cmu_Clk_5'\n   14 |     IfxGtm_Cmu_Clk_5,\n      |     ^~~~~~~~~~~~~~~~\nC:\\Users\\extpedj\\AppData\\Local\\Temp\\tdd_build_i6ir7zeo\\include/IfxGtm_Pwm.h:121:5: note: previous definition of 'IfxGtm_Cmu_Clk_5' with type 'enum <anonymous>'\n  121 |     IfxGtm_Cmu_Clk_5,\n      |     ^~~~~~~~~~~~~~~~\nC:\\Users\\extpedj\\AppData\\Local\\Temp\\tdd_build_i6ir7zeo\\include/IfxGtm_Cmu.h:15:5: error: redeclaration of enumerator 'IfxGtm_Cmu_Clk_6'\n   15 |     IfxGtm_Cmu_Clk_6,\n      |     ^~~~~~~~~~~~~~~~\nC:\\Users\\extpedj\\AppData\\Local\\Temp\\tdd_build_i6ir7zeo\\include/IfxGtm_Pwm.h:122:5: note: previous definition of 'IfxGtm_Cmu_Clk_6' with type 'enum <anonymous>'\n  122 |     IfxGtm_Cmu_Clk_6,\n      |     ^~~~~~~~~~~~~~~~\nC:\\Users\\extpedj\\AppData\\Local\\Temp\\tdd_build_i6ir7zeo\\include/IfxGtm_Cmu.h:16:5: error: redeclaration of enumerator 'IfxGtm_Cmu_Clk_7'\n   16 |     IfxGtm_Cmu_Clk_7\n      |     ^~~~~~~~~~~~~~~~\nC:\\Users\\extpedj\\AppData\\Local\\Temp\\tdd_build_i6ir7zeo\\include/IfxGtm_Pwm.h:123:5: note: previous definition of 'IfxGtm_Cmu_Clk_7' with type 'enum <anonymous>'\n  123 |     IfxGtm_Cmu_Clk_7\n      |     ^~~~~~~~~~~~~~~~\nC:\\Users\\extpedj\\AppData\\Local\\Temp\\tdd_build_i6ir7zeo\\include/IfxGtm_Cmu.h:17:3: error: conflicting types for 'IfxGtm_Cmu_Clk'; have 'enum <anonymous>'\n   17 | } IfxGtm_Cmu_Clk;\n      |   ^~~~~~~~~~~~~~\nC:\\Users\\extpedj\\AppData\\Local\\Temp\\tdd_build_i6ir7zeo\\include/IfxGtm_Pwm.h:124:3: note: previous declaration of 'IfxGtm_Cmu_Clk' with type 'IfxGtm_Cmu_Clk'\n  124 | } IfxGtm_Cmu_Clk;\n      |   ^~~~~~~~~~~~~~\nC:\\Users\\extpedj\\AppData\\Local\\Temp\\tdd_build_i6ir7zeo\\include/IfxGtm_Cmu.h:26:5: error: redeclaration of enumerator 'IfxGtm_Cmu_Fxclk_0'\n   26 |     IfxGtm_Cmu_Fxclk_0 = 0,\n      |     ^~~~~~~~~~~~~~~~~~\nC:\\Users\\extpedj\\AppData\\Local\\Temp\\tdd_build_i6ir7zeo\\include/IfxGtm_Pwm.h:127:5: note: previous definition of 'IfxGtm_Cmu_Fxclk_0' with type 'enum <anonymous>'\n  127 |     IfxGtm_Cmu_Fxclk_0 = 0,\n      |     ^~~~~~~~~~~~~~~~~~\nC:\\Users\\extpedj\\AppData\\Local\\Temp\\tdd_build_i6ir7zeo\\include/IfxGtm_Cmu.h:27:5: error: redeclaration of enumerator 'IfxGtm_Cmu_Fxclk_1'\n   27 |     IfxGtm_Cmu_Fxclk_1,\n      |     ^~~~~~~~~~~~~~~~~~\nC:\\Users\\extpedj\\AppData\\Local\\Temp\\tdd_build_i6ir7zeo\\include/IfxGtm_Pwm.h:128:5: note: previous definition of 'IfxGtm_Cmu_Fxclk_1' with type 'enum <anonymous>'\n  128 |     IfxGtm_Cmu_Fxclk_1,\n      |     ^~~~~~~~~~~~~~~~~~\nC:\\Users\\extpedj\\AppData\\Local\\Temp\\tdd_build_i6ir7zeo\\include/IfxGtm_Cmu.h:28:5: error: redeclaration of enumerator 'IfxGtm_Cmu_Fxclk_2'\n   28 |     IfxGtm_Cmu_Fxclk_2,\n      |     ^~~~~~~~~~~~~~~~~~\nC:\\Users\\extpedj\\AppData\\Local\\Temp\\tdd_build_i6ir7zeo\\include/IfxGtm_Pwm.h:129:5: note: previous definition of 'IfxGtm_Cmu_Fxclk_2' with type 'enum <anonymous>'\n  129 |     IfxGtm_Cmu_Fxclk_2,\n      |     ^~~~~~~~~~~~~~~~~~\nC:\\Users\\extpedj\\AppData\\Local\\Temp\\tdd_build_i6ir7zeo\\include/IfxGtm_Cmu.h:29:5: error: redeclaration of enumerator 'IfxGtm_Cmu_Fxclk_3'\n   29 |     IfxGtm_Cmu_Fxclk_3,\n      |     ^~~~~~~~~~~~~~~~~~\nC:\\Users\\extpedj\\AppData\\Local\\Temp\\tdd_build_i6ir7zeo\\include/IfxGtm_Pwm.h:130:5: note: previous definition of 'IfxGtm_Cmu_Fxclk_3' with type 'enum <anonymous>'\n  130 |     IfxGtm_Cmu_Fxclk_3,\n      |     ^~~~~~~~~~~~~~~~~~\nC:\\Users\\extpedj\\AppData\\Local\\Temp\\tdd_build_i6ir7zeo\\include/IfxGtm_Cmu.h:30:5: error: redeclaration of enumerator 'IfxGtm_Cmu_Fxclk_4'\n   30 |     IfxGtm_Cmu_Fxclk_4\n      |     ^~~~~~~~~~~~~~~~~~\nC:\\Users\\extpedj\\AppData\\Local\\Temp\\tdd_build_i6ir7zeo\\include/IfxGtm_Pwm.h:131:5: note: previous definition of 'IfxGtm_Cmu_Fxclk_4' with type 'enum <anonymous>'\n  131 |     IfxGtm_Cmu_Fxclk_4\n      |     ^~~~~~~~~~~~~~~~~~\nC:\\Users\\extpedj\\AppData\\Local\\Temp\\tdd_build_i6ir7zeo\\include/IfxGtm_Cmu.h:31:3: error: conflicting types for 'IfxGtm_Cmu_Fxclk'; have 'enum <anonymous>'\n   31 | } IfxGtm_Cmu_Fxclk;\n      |   ^~~~~~~~~~~~~~~~\nC:\\Users\\extpedj\\AppData\\Local\\Temp\\tdd_build_i6ir7zeo\\include/IfxGtm_Pwm.h:132:3: note: previous declaration of 'IfxGtm_Cmu_Fxclk' with type 'IfxGtm_Cmu_Fxclk'\n  132 | } IfxGtm_Cmu_Fxclk;\n      |   ^~~~~~~~~~~~~~~~\n\nIn file included from C:\\Users\\extpedj\\Desktop\\infineon_POC_MVP\\unity/unity.h:22,\n                 from C:\\Users\\extpedj\\AppData\\Local\\Temp\\tdd_build_i6ir7zeo\\test\\test_gtm_tom_3_phase_inverter_pwm.c:1:\nC:\\Users\\extpedj\\AppData\\Local\\Temp\\tdd_build_i6ir7zeo\\test\\test_gtm_tom_3_phase_inverter_pwm.c: In function 'test_TC_G1_001_init_enables_gtm_clocks_and_inits_pwm_once':\nC:\\Users\\extpedj\\AppData\\Local\\Temp\\tdd_build_i6ir7zeo\\test\\test_gtm_tom_3_phase_inverter_pwm.c:37:85: warning: comparison of integer expressions of different signedness: 'int' and 'unsigned int' [-Wsign-compare]\n   37 |     TEST_ASSERT_TRUE_MESSAGE((mock_IfxGtm_Tom_Timer_addToChannelMask_getCallCount() >= 1U), \"Timer addToChannelMask should be called at least once to include all three channels in update mask\");\n      |                                                                                     ^~\nC:\\Users\\extpedj\\Desktop\\infineon_POC_MVP\\unity/unity_internals.h:891:107: note: in definition of macro 'UNITY_TEST_ASSERT'\n  891 | #define UNITY_TEST_ASSERT(condition, line, message)                                              do { if (condition) { /* nothing*/ } else { UNITY_TEST_FAIL((line), (message)); } } while (0)\n      |                                                                                                           ^~~~~~~~~\nC:\\Users\\extpedj\\AppData\\Local\\Temp\\tdd_build_i6ir7zeo\\test\\test_gtm_tom_3_phase_inverter_pwm.c:37:5: note: in expansion of macro 'TEST_ASSERT_TRUE_MESSAGE'\n   37 |     TEST_ASSERT_TRUE_MESSAGE((mock_IfxGtm_Tom_Timer_addToChannelMask_getCallCount() >= 1U), \"Timer addToChannelMask should be called at least once to include all three channels in update mask\");\n      |     ^~~~~~~~~~~~~~~~~~~~~~~~\nC:\\Users\\extpedj\\AppData\\Local\\Temp\\tdd_build_i6ir7zeo\\test\\test_gtm_tom_3_phase_inverter_pwm.c: In function 'test_TC_G2_002_init_stages_initial_duties_and_applies_shadow_transfer':\nC:\\Users\\extpedj\\AppData\\Local\\Temp\\tdd_build_i6ir7zeo\\test\\test_gtm_tom_3_phase_inverter_pwm.c:97:41: error: implicit declaration of function 'mock_IfxGtm_Pwm_updateChannelDeadTimeImmediate_getCallCount'; did you mean 'mock_IfxGtm_Pwm_updateChannelsDuty_getCallCount'? [-Wimplicit-function-declaration]\n   97 |     TEST_ASSERT_EQUAL_UINT32_MESSAGE(0, mock_IfxGtm_Pwm_updateChannelDeadTimeImmediate_getCallCount(), \"Dead-time should not be configured for single-ended PWM (call count must be 0)\");\n      |                                         ^~~~~~~~~~~~~~~~~~~~~~~~~~~~~~~~~~~~~~~~~~~~~~~~~~~~~~~~~~~\nC:\\Users\\extpedj\\Desktop\\infineon_POC_MVP\\unity/unity_internals.h:904:184: note: in definition of macro 'UNITY_TEST_ASSERT_EQUAL_UINT32'\n  904 | #define UNITY_TEST_ASSERT_EQUAL_UINT32(expected, actual, line, message)                          UnityAssertEqualNumber((UNITY_INT)(UNITY_UINT32)(expected), (UNITY_INT)(UNITY_UINT32)(actual), (message), (UNITY_LINE_TYPE)(line), UNITY_DISPLAY_STYLE_UINT32)\n      |                                                                                                                                                                                        ^~~~~~\nC:\\Users\\extpedj\\AppData\\Local\\Temp\\tdd_build_i6ir7zeo\\test\\test_gtm_tom_3_phase_inverter_pwm.c:97:5: note: in expansion of macro 'TEST_ASSERT_EQUAL_UINT32_MESSAGE'\n   97 |     TEST_ASSERT_EQUAL_UINT32_MESSAGE(0, mock_IfxGtm_Pwm_updateChannelDeadTimeImmediate_getCallCount(), \"Dead-time should not be configured for single-ended PWM (call count must be 0)\");\n      |     ^~~~~~~~~~~~~~~~~~~~~~~~~~~~~~~~\n",
  "stdout": ""
}